[
  {
    "name": "AAAuraDamage",
    "value": 1.1,
    "gameLocalizationKey": "PARAMS_MODIFIER_AAAURADAMAGE_DESTROYER",
    "appLocalizationKey": null,
    "unit": "Percent",
    "affectedProperties": [
      "AntiAirDataContainer.ConstantDamage"
    ],
    "displayedValueProcessingKind": "DecimalRoundedPercentage",
    "valueProcessingKind": "Multiplier"
  },
  {
    "name": "AAAuraDamage_AirCarrier",
    "value": 1.1,
    "gameLocalizationKey": "PARAMS_MODIFIER_AAAURADAMAGE_AIRCARRIER",
    "appLocalizationKey": null,
    "unit": "Percent",
    "affectedProperties": [
      "AntiAirDataContainer.ConstantDamage"
    ],
    "displayedValueProcessingKind": "DecimalRoundedPercentage",
    "valueProcessingKind": "Multiplier"
  },
  {
    "name": "AAAuraDamage_Battleship",
    "value": 1.15,
    "gameLocalizationKey": "PARAMS_MODIFIER_AAAURADAMAGE_BATTLESHIP",
    "appLocalizationKey": null,
    "unit": "Percent",
    "affectedProperties": [
      "AntiAirDataContainer.ConstantDamage"
    ],
    "displayedValueProcessingKind": "DecimalRoundedPercentage",
    "valueProcessingKind": "Multiplier"
  },
  {
    "name": "AAAuraDamage_Cruiser",
    "value": 1.25,
    "gameLocalizationKey": "PARAMS_MODIFIER_AAAURADAMAGE_CRUISER",
    "appLocalizationKey": null,
    "unit": "Percent",
    "affectedProperties": [
      "AntiAirDataContainer.ConstantDamage"
    ],
    "displayedValueProcessingKind": "DecimalRoundedPercentage",
    "valueProcessingKind": "Multiplier"
  },
  {
    "name": "AAAuraDamage_Destroyer",
    "value": 1,
    "gameLocalizationKey": "PARAMS_MODIFIER_AAAURADAMAGE_DESTROYER",
    "appLocalizationKey": null,
    "unit": "None",
    "affectedProperties": [
      "AntiAirDataContainer.ConstantDamage"
    ],
    "displayedValueProcessingKind": "ToInt",
    "valueProcessingKind": "Multiplier"
  },
  {
    "name": "AAAuraDamage_Submarine",
    "value": 1,
    "gameLocalizationKey": "PARAMS_MODIFIER_AAAURADAMAGE_SUBMARINE",
    "appLocalizationKey": null,
    "unit": "None",
    "affectedProperties": [
      "AntiAirDataContainer.ConstantDamage"
    ],
    "displayedValueProcessingKind": "ToInt",
    "valueProcessingKind": "Multiplier"
  },
  {
    "name": "AAAuraReceiveDamageCoeff",
    "value": 0.9,
    "gameLocalizationKey": "PARAMS_MODIFIER_AAAURARECEIVEDAMAGECOEFF",
    "appLocalizationKey": null,
    "unit": "Percent",
    "affectedProperties": [],
    "displayedValueProcessingKind": "DecimalRoundedPercentage",
    "valueProcessingKind": "None"
  },
  {
    "name": "AABubbleDamage",
    "value": 1.15,
    "gameLocalizationKey": "PARAMS_MODIFIER_AABUBBLEDAMAGE_DESTROYER",
    "appLocalizationKey": null,
    "unit": "Percent",
    "affectedProperties": [
      "AntiAirDataContainer.FlakDamage"
    ],
    "displayedValueProcessingKind": "DecimalRoundedPercentage",
    "valueProcessingKind": "Multiplier"
  },
  {
    "name": "AABubbleDamage_AirCarrier",
    "value": 1.1,
    "gameLocalizationKey": "PARAMS_MODIFIER_AABUBBLEDAMAGE_AIRCARRIER",
    "appLocalizationKey": null,
    "unit": "Percent",
    "affectedProperties": [
      "AntiAirDataContainer.FlakDamage"
    ],
    "displayedValueProcessingKind": "DecimalRoundedPercentage",
    "valueProcessingKind": "Multiplier"
  },
  {
    "name": "AABubbleDamage_Battleship",
    "value": 1.15,
    "gameLocalizationKey": "PARAMS_MODIFIER_AABUBBLEDAMAGE_BATTLESHIP",
    "appLocalizationKey": null,
    "unit": "Percent",
    "affectedProperties": [
      "AntiAirDataContainer.FlakDamage"
    ],
    "displayedValueProcessingKind": "DecimalRoundedPercentage",
    "valueProcessingKind": "Multiplier"
  },
  {
    "name": "AABubbleDamage_Cruiser",
    "value": 1.25,
    "gameLocalizationKey": "PARAMS_MODIFIER_AABUBBLEDAMAGE_CRUISER",
    "appLocalizationKey": null,
    "unit": "Percent",
    "affectedProperties": [
      "AntiAirDataContainer.FlakDamage"
    ],
    "displayedValueProcessingKind": "DecimalRoundedPercentage",
    "valueProcessingKind": "Multiplier"
  },
  {
    "name": "AABubbleDamage_Destroyer",
    "value": 1,
    "gameLocalizationKey": "PARAMS_MODIFIER_AABUBBLEDAMAGE_DESTROYER",
    "appLocalizationKey": null,
    "unit": "None",
    "affectedProperties": [
      "AntiAirDataContainer.FlakDamage"
    ],
    "displayedValueProcessingKind": "ToInt",
    "valueProcessingKind": "Multiplier"
  },
  {
    "name": "AABubbleDamage_Submarine",
    "value": 1,
    "gameLocalizationKey": "PARAMS_MODIFIER_AABUBBLEDAMAGE_SUBMARINE",
    "appLocalizationKey": null,
    "unit": "None",
    "affectedProperties": [
      "AntiAirDataContainer.FlakDamage"
    ],
    "displayedValueProcessingKind": "ToInt",
    "valueProcessingKind": "Multiplier"
  },
  {
    "name": "AAExtraBubbles",
    "value": 1,
    "gameLocalizationKey": "PARAMS_MODIFIER_AAEXTRABUBBLES_SKILL",
    "appLocalizationKey": null,
    "unit": "None",
    "affectedProperties": [
      "AntiAirDataContainer.FlakAmount"
    ],
    "displayedValueProcessingKind": "ToInt",
    "valueProcessingKind": "DirectAdd"
  },
  {
    "name": "AAInnerExtraBubbles",
    "value": 2,
    "gameLocalizationKey": "PARAMS_MODIFIER_AAINNEREXTRABUBBLES",
    "appLocalizationKey": null,
    "unit": "None",
    "affectedProperties": [
      "AntiAirDataContainer.FlakAmount"
    ],
    "displayedValueProcessingKind": "ToInt",
    "valueProcessingKind": "DirectAdd"
  },
  {
    "name": "AAMaxHP",
    "value": 2,
    "gameLocalizationKey": "PARAMS_MODIFIER_AAMAXHP_DESTROYER",
    "appLocalizationKey": null,
    "unit": "Percent",
    "affectedProperties": [],
    "displayedValueProcessingKind": "VariablePercentage",
    "valueProcessingKind": "None"
  },
  {
    "name": "AAMaxHP_AirCarrier",
    "value": 1,
    "gameLocalizationKey": "PARAMS_MODIFIER_AAMAXHP_AIRCARRIER",
    "appLocalizationKey": null,
    "unit": "Percent",
    "affectedProperties": [],
    "displayedValueProcessingKind": "VariablePercentage",
    "valueProcessingKind": "None"
  },
  {
    "name": "AAMaxHP_Battleship",
    "value": 1.15,
    "gameLocalizationKey": "PARAMS_MODIFIER_AAMAXHP_BATTLESHIP",
    "appLocalizationKey": null,
    "unit": "Percent",
    "affectedProperties": [],
    "displayedValueProcessingKind": "VariablePercentage",
    "valueProcessingKind": "None"
  },
  {
    "name": "AAMaxHP_Cruiser",
    "value": 1,
    "gameLocalizationKey": "PARAMS_MODIFIER_AAMAXHP_CRUISER",
    "appLocalizationKey": null,
    "unit": "Percent",
    "affectedProperties": [],
    "displayedValueProcessingKind": "VariablePercentage",
    "valueProcessingKind": "None"
  },
  {
    "name": "AAMaxHP_Destroyer",
    "value": 1.15,
    "gameLocalizationKey": "PARAMS_MODIFIER_AAMAXHP_DESTROYER",
    "appLocalizationKey": null,
    "unit": "Percent",
    "affectedProperties": [],
    "displayedValueProcessingKind": "VariablePercentage",
    "valueProcessingKind": "None"
  },
  {
    "name": "AAMaxHP_Submarine",
    "value": 1,
    "gameLocalizationKey": "PARAMS_MODIFIER_AAMAXHP_SUBMARINE",
    "appLocalizationKey": null,
    "unit": "Percent",
    "affectedProperties": [],
    "displayedValueProcessingKind": "VariablePercentage",
    "valueProcessingKind": "None"
  },
  {
    "name": "additionalConsumables",
    "value": 1,
    "gameLocalizationKey": "PARAMS_MODIFIER_ADDITIONALCONSUMABLES",
    "appLocalizationKey": null,
    "unit": "None",
    "affectedProperties": [
      "ConsumableDataContainer.Uses.Ship"
    ],
    "displayedValueProcessingKind": "ToInt",
    "valueProcessingKind": "DirectAdd"
  },
  {
    "name": "airDefenseDispReloadCoeff",
    "value": 0.9,
    "gameLocalizationKey": "PARAMS_MODIFIER_AIRDEFENSEDISPRELOADCOEFF_MODERNIZATION",
    "appLocalizationKey": null,
    "unit": "Percent",
    "affectedProperties": [
      "ConsumableDataContainer.Reload.PCY011"
    ],
    "displayedValueProcessingKind": "DecimalRoundedPercentage",
    "valueProcessingKind": "Multiplier"
  },
  {
    "name": "airDefenseDispWorkTimeCoeff",
    "value": 1.2,
    "gameLocalizationKey": "PARAMS_MODIFIER_AIRDEFENSEDISPWORKTIMECOEFF_MODERNIZATION",
    "appLocalizationKey": null,
    "unit": "Percent",
    "affectedProperties": [
      "ConsumableDataContainer.WorkTime.PCY011"
    ],
    "displayedValueProcessingKind": "DecimalRoundedPercentage",
    "valueProcessingKind": "Multiplier"
  },
  {
    "name": "allConsumableReloadTime",
    "value": 0.925,
    "gameLocalizationKey": "PARAMS_MODIFIER_ALLCONSUMABLERELOADTIME",
    "appLocalizationKey": null,
    "unit": "Percent",
    "affectedProperties": [],
    "displayedValueProcessingKind": "DecimalRoundedPercentage",
    "valueProcessingKind": "None"
  },
  {
    "name": "areaDamageMultiplier",
    "value": 1.5,
    "gameLocalizationKey": "PARAMS_MODIFIER_AREADAMAGEMULTIPLIER",
    "appLocalizationKey": null,
    "unit": "Percent",
    "affectedProperties": [
      "AntiAirDataContainer.ConstantDamage"
    ],
    "displayedValueProcessingKind": "DecimalRoundedPercentage",
    "valueProcessingKind": "Multiplier"
  },
  {
    "name": "artilleryAlertMinDistance",
    "value": 150,
    "gameLocalizationKey": null,
    "appLocalizationKey": "IncomingFireAlertDesc",
    "unit": "KM",
    "affectedProperties": [],
    "displayedValueProcessingKind": "BigWorldToKm",
    "valueProcessingKind": "None"
  },
  {
    "name": "artilleryBurnChanceBonus_AirCarrier",
    "value": 0,
    "gameLocalizationKey": "PARAMS_MODIFIER_ARTILLERYBURNCHANCEBONUS_AIRCARRIER",
    "appLocalizationKey": null,
    "unit": "Percent",
    "affectedProperties": [
      "ShellDataContainer.FireChance"
    ],
    "displayedValueProcessingKind": "NoneOrPercentage",
    "valueProcessingKind": "SumPercentage"
  },
  {
    "name": "artilleryBurnChanceBonus_Battleship",
    "value": 0.01,
    "gameLocalizationKey": "PARAMS_MODIFIER_ARTILLERYBURNCHANCEBONUS_BATTLESHIP",
    "appLocalizationKey": null,
    "unit": "Percent",
    "affectedProperties": [
      "ShellDataContainer.FireChance"
    ],
    "displayedValueProcessingKind": "NoneOrPercentage",
    "valueProcessingKind": "SumPercentage"
  },
  {
    "name": "artilleryBurnChanceBonus_Cruiser",
    "value": 0.01,
    "gameLocalizationKey": "PARAMS_MODIFIER_ARTILLERYBURNCHANCEBONUS_CRUISER",
    "appLocalizationKey": null,
    "unit": "Percent",
    "affectedProperties": [
      "ShellDataContainer.FireChance"
    ],
    "displayedValueProcessingKind": "NoneOrPercentage",
    "valueProcessingKind": "SumPercentage"
  },
  {
    "name": "artilleryBurnChanceBonus_Destroyer",
    "value": 0.01,
    "gameLocalizationKey": "PARAMS_MODIFIER_ARTILLERYBURNCHANCEBONUS_DESTROYER",
    "appLocalizationKey": null,
    "unit": "Percent",
    "affectedProperties": [
      "ShellDataContainer.FireChance"
    ],
    "displayedValueProcessingKind": "NoneOrPercentage",
    "valueProcessingKind": "SumPercentage"
  },
  {
    "name": "artilleryBurnChanceBonus_Submarine",
    "value": 0,
    "gameLocalizationKey": "PARAMS_MODIFIER_ARTILLERYBURNCHANCEBONUS_SUBMARINE",
    "appLocalizationKey": null,
    "unit": "Percent",
    "affectedProperties": [
      "ShellDataContainer.FireChance"
    ],
    "displayedValueProcessingKind": "NoneOrPercentage",
    "valueProcessingKind": "SumPercentage"
  },
  {
    "name": "artilleryDistCoeff",
    "value": 1.2,
    "gameLocalizationKey": "PARAMS_MODIFIER_ARTILLERYDISTCOEFF",
    "appLocalizationKey": null,
    "unit": "Percent",
    "affectedProperties": [
      "MainBatteryDataContainer.Range"
    ],
    "displayedValueProcessingKind": "DecimalRoundedPercentage",
    "valueProcessingKind": "Multiplier"
  },
  {
    "name": "artilleryKruppMultiplier",
    "value": 2,
    "gameLocalizationKey": "PARAMS_MODIFIER_ARTILLERYKRUPPMULTIPLIER",
    "appLocalizationKey": null,
    "unit": "None",
    "affectedProperties": ["ShellDataContainer.Krupp"],
    "displayedValueProcessingKind": "DecimalRoundedPercentage",
    "valueProcessingKind": "Multiplier"
  },
  {
    "name": "artilleryReloadCoeff",
    "value": 0.667,
    "gameLocalizationKey": "PARAMS_MODIFIER_ARTILLERYRELOADCOEFF_SKILL",
    "appLocalizationKey": null,
    "unit": "Percent",
    "affectedProperties": [
      "MainBatteryDataContainer.Reload"
    ],
    "displayedValueProcessingKind": "DecimalRoundedPercentage",
    "valueProcessingKind": "Multiplier"
  },
  {
    "name": "asMaxHealthCoeff",
    "value": 1.25,
    "gameLocalizationKey": "PARAMS_MODIFIER_ASMAXHEALTHCOEFF",
    "appLocalizationKey": null,
    "unit": "Percent",
    "affectedProperties": [
      "AirstrikeDataContainer.PlaneHp"
    ],
    "displayedValueProcessingKind": "DecimalRoundedPercentage",
    "valueProcessingKind": "Multiplier"
  },
  {
    "name": "asReloadTimeCoeff",
    "value": 0.85,
    "gameLocalizationKey": "PARAMS_MODIFIER_ASRELOADTIMECOEFF",
    "appLocalizationKey": null,
    "unit": "Percent",
    "affectedProperties": [
      "AirstrikeDataContainer.Reload"
    ],
    "displayedValueProcessingKind": "DecimalRoundedPercentage",
    "valueProcessingKind": "Multiplier"
  },
  {
    "name": "backwardEngineForsag",
    "value": 4,
    "gameLocalizationKey": "",
    "appLocalizationKey": null,
    "unit": "Percent",
    "affectedProperties": [
      "ManeuverabilityDataContainer.BackwardEngineForsag.SpeedBoost"
    ],
    "displayedValueProcessingKind": "DecimalRoundedPercentage",
    "valueProcessingKind": "DirectAdd"
  },
  {
    "name": "backwardEngineForsagMaxSpeed",
    "value": 12,
    "gameLocalizationKey": "",
    "appLocalizationKey": null,
    "unit": "None",
    "affectedProperties": [
      "ManeuverabilityDataContainer.BackwardEngineForsagMaxSpeed.SpeedBoost"
    ],
    "displayedValueProcessingKind": "ToInt",
    "valueProcessingKind": "DirectAdd"
  },
  {
    "name": "batteryCapacityCoeff",
    "value": 1.1,
    "gameLocalizationKey": "PARAMS_MODIFIER_BATTERYCAPACITYCOEFF",
    "appLocalizationKey": null,
    "unit": "Percent",
    "affectedProperties": [
      "SurvivabilityDataContainer.DiveCapacity"
    ],
    "displayedValueProcessingKind": "DecimalRoundedPercentage",
    "valueProcessingKind": "Multiplier"
  },
  {
    "name": "batteryRegenCoeff",
    "value": 1.25,
    "gameLocalizationKey": "PARAMS_MODIFIER_BATTERYREGENCOEFF",
    "appLocalizationKey": null,
    "unit": "Percent",
    "affectedProperties": [
      "SurvivabilityDataContainer.DiveCapacityRecharge"
    ],
    "displayedValueProcessingKind": "DecimalRoundedPercentage",
    "valueProcessingKind": "Multiplier"
  },
  {
    "name": "bombAlphaDamageMultiplier",
    "value": 1.1,
    "gameLocalizationKey": "PARAMS_MODIFIER_BOMBALPHADAMAGEMULTIPLIER",
    "appLocalizationKey": null,
    "unit": "Percent",
    "affectedProperties": [
      "BombDataContainer.Damage.He"
    ],
    "displayedValueProcessingKind": "DecimalRoundedPercentage",
    "valueProcessingKind": "Multiplier"
  },
  {
    "name": "bombApAlphaDamageMultiplier",
    "value": 1.03,
    "gameLocalizationKey": "PARAMS_MODIFIER_BOMBAPALPHADAMAGEMULTIPLIER",
    "appLocalizationKey": null,
    "unit": "Percent",
    "affectedProperties": [
      "BombDataContainer.Damage.Ap"
    ],
    "displayedValueProcessingKind": "DecimalRoundedPercentage",
    "valueProcessingKind": "Multiplier"
  },
  {
    "name": "bombBurnChanceBonus",
    "value": 0.05,
    "gameLocalizationKey": "PARAMS_MODIFIER_BOMBBURNCHANCEBONUS",
    "appLocalizationKey": null,
    "unit": "Percent",
    "affectedProperties": [
      "BombDataContainer.FireChance"
    ],
    "displayedValueProcessingKind": "NoneOrPercentage",
    "valueProcessingKind": "SumPercentage"
  },
  {
    "name": "boostCoeff",
    "value": 0.2,
    "gameLocalizationKey": "PARAMS_MODIFIER_BOOSTCOEFF",
    "appLocalizationKey": null,
    "unit": "Percent",
    "affectedProperties": [
      "ManeuverabilityDataContainer.BoostCoeff"
    ],
    "displayedValueProcessingKind": "RoundedPercentage",
    "valueProcessingKind": "DirectAdd"
  },
  {
    "name": "boostCoeffForsage",
    "value": 0.08,
    "gameLocalizationKey": "PARAMS_MODIFIER_BOOSTCOEFFFORSAGE",
    "appLocalizationKey": null,
    "unit": "Percent",
    "affectedProperties": [
      "ManeuverabilityDataContainer.SpeedBoostForsage"
    ],
    "displayedValueProcessingKind": "RoundedPercentage",
    "valueProcessingKind": "DirectAdd"
  },
  {
    "name": "bubbleDamageMultiplier",
    "value": 4,
    "gameLocalizationKey": "PARAMS_MODIFIER_BUBBLEDAMAGEMULTIPLIER",
    "appLocalizationKey": null,
    "unit": "Percent",
    "affectedProperties": [
      "AntiAirDataContainer.FlakDamage"
    ],
    "displayedValueProcessingKind": "PositivePercentage",
    "valueProcessingKind": "Multiplier"
  },
  {
    "name": "buoyancyRudderResetTimeCoeff",
    "value": 0.9,
    "gameLocalizationKey": "PARAMS_MODIFIER_BUOYANCYRUDDERRESETTIMECOEFF",
    "appLocalizationKey": null,
    "unit": "Percent",
    "affectedProperties": [],
    "displayedValueProcessingKind": "DecimalRoundedPercentage",
    "valueProcessingKind": "None"
  },
  {
    "name": "buoyancyRudderTimeCoeff",
    "value": 0.9,
    "gameLocalizationKey": "PARAMS_MODIFIER_BUOYANCYRUDDERTIMECOEFF",
    "appLocalizationKey": null,
    "unit": "Percent",
    "affectedProperties": [
      "ManeuverabilityDataContainer.DivingPlaneShiftTime"
    ],
    "displayedValueProcessingKind": "DecimalRoundedPercentage",
    "valueProcessingKind": "Multiplier"
  },
  {
    "name": "burnChanceBonus",
    "value": 0.01,
    "gameLocalizationKey": "PARAMS_MODIFIER_BURNCHANCEBONUS",
    "appLocalizationKey": null,
    "unit": "Percent",
    "affectedProperties": [
      "ShellDataContainer.FireChance"
    ],
    "displayedValueProcessingKind": "NoneOrPercentage",
    "valueProcessingKind": "SumPercentage"
  },
  {
    "name": "burnChanceFactorBig",
    "value": 0,
    "gameLocalizationKey": "PARAMS_MODIFIER_BURNCHANCEFACTORBIG",
    "appLocalizationKey": null,
    "unit": "Percent",
    "affectedProperties": [
      "ShellDataContainer.FireChance.Big.Additive",
      "BombDataContainer.FireChance"
    ],
    "displayedValueProcessingKind": "NoneOrPercentage",
    "valueProcessingKind": "SumPercentage"
  },
  {
    "name": "burnChanceFactorHighLevel",
    "value": 0.5,
    "gameLocalizationKey": "PARAMS_MODIFIER_BURNCHANCEFACTORHIGHLEVEL",
    "appLocalizationKey": null,
    "unit": "Percent",
    "affectedProperties": [
      "ShellDataContainer.FireChance.Big.Multiplier"
    ],
    "displayedValueProcessingKind": "NegativePercentage",
    "valueProcessingKind": "Multiplier"
  },
  {
    "name": "burnChanceFactorLowLevel",
    "value": 0.5,
    "gameLocalizationKey": "PARAMS_MODIFIER_BURNCHANCEFACTORLOWLEVEL",
    "appLocalizationKey": null,
    "unit": "Percent",
    "affectedProperties": [
      "ShellDataContainer.FireChance.Small.Multiplier"
    ],
    "displayedValueProcessingKind": "NegativePercentage",
    "valueProcessingKind": "Multiplier"
  },
  {
    "name": "burnChanceFactorSmall",
    "value": 0.005,
    "gameLocalizationKey": "PARAMS_MODIFIER_BURNCHANCEFACTORSMALL",
    "appLocalizationKey": null,
    "unit": "Percent",
    "affectedProperties": [
      "ShellDataContainer.FireChance.Small.Additive",
      "RocketDataContainer.FireChance"
    ],
    "displayedValueProcessingKind": "NoneOrPercentage",
    "valueProcessingKind": "SumPercentage"
  },
  {
    "name": "burnProb",
    "value": 0.9,
    "gameLocalizationKey": "PARAMS_MODIFIER_BURNPROB",
    "appLocalizationKey": null,
    "unit": "Percent",
    "affectedProperties": [
      "SurvivabilityDataContainer.FireChanceResistance"
    ],
    "displayedValueProcessingKind": "DecimalRoundedPercentage",
    "valueProcessingKind": "Multiplier"
  },
  {
    "name": "burnTime",
    "value": 1.25,
    "gameLocalizationKey": "PARAMS_MODIFIER_BURNTIME",
    "appLocalizationKey": null,
    "unit": "Percent",
    "affectedProperties": [
      "SurvivabilityDataContainer.FireDuration"
    ],
    "displayedValueProcessingKind": "DecimalRoundedPercentage",
    "valueProcessingKind": "Multiplier"
  },
  {
    "name": "callFightersAdditionalConsumables",
    "value": 1,
    "gameLocalizationKey": "PARAMS_MODIFIER_CALLFIGHTERSADDITIONALCONSUMABLES_SKILL",
    "appLocalizationKey": null,
    "unit": "None",
    "affectedProperties": [
      "ConsumableDataContainer.Uses.PCY035"
    ],
    "displayedValueProcessingKind": "ToInt",
    "valueProcessingKind": "DirectAdd"
  },
  {
    "name": "callFightersAppearDelay",
    "value": 1.5,
    "gameLocalizationKey": "PARAMS_MODIFIER_CALLFIGHTERSAPPEARDELAY",
    "appLocalizationKey": null,
    "unit": "Percent",
    "affectedProperties": [
      "ConsumableDataContainer.TimeDelayAppear.PCY035"
    ],
    "displayedValueProcessingKind": "DecimalRoundedPercentage",
    "valueProcessingKind": "Multiplier"
  },
  {
    "name": "callFightersRadiusCoeff",
    "value": 1.1,
    "gameLocalizationKey": "PARAMS_MODIFIER_CALLFIGHTERSRADIUSCOEFF",
    "appLocalizationKey": null,
    "unit": "Percent",
    "affectedProperties": [
      "ConsumableDataContainer.Radius.PCY035"
    ],
    "displayedValueProcessingKind": "DecimalRoundedPercentage",
    "valueProcessingKind": "Multiplier"
  },
  {
    "name": "callFightersTimeDelayAttack",
    "value": 0.2,
    "gameLocalizationKey": "PARAMS_MODIFIER_CALLFIGHTERSTIMEDELAYATTACK",
    "appLocalizationKey": null,
    "unit": "Percent",
    "affectedProperties": [
      "ConsumableDataContainer.TimeDelayAttack.PCY035"
    ],
    "displayedValueProcessingKind": "InverseNegativePercentage",
    "valueProcessingKind": "Multiplier"
  },
  {
    "name": "callFightersWorkTimeCoeff",
    "value": 1.25,
    "gameLocalizationKey": "PARAMS_MODIFIER_CALLFIGHTERSWORKTIMECOEFF_SKILL",
    "appLocalizationKey": null,
    "unit": "Percent",
    "affectedProperties": [
      "ConsumableDataContainer.WorkTime.PCY035"
    ],
    "displayedValueProcessingKind": "DecimalRoundedPercentage",
    "valueProcessingKind": "Multiplier"
  },
  {
    "name": "captain_PGW103_Lutjens_regenerationHPSpeed",
    "value": 300,
    "gameLocalizationKey": "PARAMS_MODIFIER_REGENERATIONHPSPEED",
    "appLocalizationKey": null,
    "unit": "None",
    "affectedProperties": [],
    "displayedValueProcessingKind": "None",
    "valueProcessingKind": "None"
  },
  {
    "name": "captain_PJW018_Yamamoto_regenerationHPSpeed",
    "value": 0.004,
    "gameLocalizationKey": "PARAMS_MODIFIER_REGENERATIONHPSPEED_WITH_WORKTIME_CUSTOM",
    "appLocalizationKey": null,
    "unit": "Percent",
    "affectedProperties": [],
    "displayedValueProcessingKind": "DecimalRoundedPercentage",
    "valueProcessingKind": "None"
  },
  {
    "name": "captain_PRW406_Kuznetsov_regenerationHPSpeed",
    "value": 0.0035,
    "gameLocalizationKey": "PARAMS_MODIFIER_REGENERATIONHPSPEED",
    "appLocalizationKey": null,
    "unit": "Percent",
    "affectedProperties": [],
    "displayedValueProcessingKind": "DecimalRoundedPercentage",
    "valueProcessingKind": "None"
  },
  {
    "name": "climbAngle",
    "value": 55,
    "gameLocalizationKey": "",
    "appLocalizationKey": null,
    "unit": "None",
    "affectedProperties": [],
    "displayedValueProcessingKind": "ToInt",
    "valueProcessingKind": "None"
  },
  {
    "name": "collisionDamageApply",
    "value": 1.5,
    "gameLocalizationKey": "PARAMS_MODIFIER_COLLISIONDAMAGEAPPLY",
    "appLocalizationKey": null,
    "unit": "Percent",
    "affectedProperties": [],
    "displayedValueProcessingKind": "DecimalRoundedPercentage",
    "valueProcessingKind": "None"
  },
  {
    "name": "collisionDamageNerf",
    "value": 0.8,
    "gameLocalizationKey": "PARAMS_MODIFIER_COLLISIONDAMAGENERF",
    "appLocalizationKey": null,
    "unit": "Percent",
    "affectedProperties": [],
    "displayedValueProcessingKind": "DecimalRoundedPercentage",
    "valueProcessingKind": "None"
  },
  {
    "name": "consumable_regenerationHPSpeed",
    "value": 0.005,
    "gameLocalizationKey": "PARAMS_MODIFIER_REGENERATIONHPSPEED",
    "appLocalizationKey": null,
    "unit": "Percent",
    "affectedProperties": [],
    "displayedValueProcessingKind": "DecimalRoundedPercentage",
    "valueProcessingKind": "None"
  },
  {
    "name": "ConsumableReloadTime",
    "value": 0.85,
    "gameLocalizationKey": "PARAMS_MODIFIER_CONSUMABLERELOADTIME_DESTROYER",
    "appLocalizationKey": null,
    "unit": "Percent",
    "affectedProperties": [
      "ConsumableDataContainer.Reload.Ship",
      "ConsumableDataContainer.PrepTime.PCY048"
    ],
    "displayedValueProcessingKind": "DecimalRoundedPercentage",
    "valueProcessingKind": "Multiplier"
  },
  {
    "name": "ConsumableReloadTime_AirCarrier",
    "value": 1,
    "gameLocalizationKey": "PARAMS_MODIFIER_CONSUMABLERELOADTIME_AIRCARRIER",
    "appLocalizationKey": null,
    "unit": "Percent",
    "affectedProperties": [
      "ConsumableDataContainer.Reload.AirCarrier"
    ],
    "displayedValueProcessingKind": "DecimalRoundedPercentage",
    "valueProcessingKind": "Multiplier"
  },
  {
    "name": "ConsumableReloadTime_Battleship",
    "value": 0.6,
    "gameLocalizationKey": "PARAMS_MODIFIER_CONSUMABLERELOADTIME_BATTLESHIP",
    "appLocalizationKey": null,
    "unit": "Percent",
    "affectedProperties": [
      "ConsumableDataContainer.Reload.Battleship"
    ],
    "displayedValueProcessingKind": "DecimalRoundedPercentage",
    "valueProcessingKind": "Multiplier"
  },
  {
    "name": "ConsumableReloadTime_Cruiser",
    "value": 0.5,
    "gameLocalizationKey": "PARAMS_MODIFIER_CONSUMABLERELOADTIME_CRUISER",
    "appLocalizationKey": null,
    "unit": "Percent",
    "affectedProperties": [
      "ConsumableDataContainer.Reload.Cruiser"
    ],
    "displayedValueProcessingKind": "DecimalRoundedPercentage",
    "valueProcessingKind": "Multiplier"
  },
  {
    "name": "ConsumableReloadTime_Destroyer",
    "value": 1,
    "gameLocalizationKey": "PARAMS_MODIFIER_CONSUMABLERELOADTIME_DESTROYER",
    "appLocalizationKey": null,
    "unit": "Percent",
    "affectedProperties": [
      "ConsumableDataContainer.Reload.Destroyer"
    ],
    "displayedValueProcessingKind": "DecimalRoundedPercentage",
    "valueProcessingKind": "Multiplier"
  },
  {
    "name": "ConsumableReloadTime_Submarine",
    "value": 1,
    "gameLocalizationKey": "PARAMS_MODIFIER_CONSUMABLERELOADTIME_SUBMARINE",
    "appLocalizationKey": null,
    "unit": "Percent",
    "affectedProperties": [
      "ConsumableDataContainer.Reload.Submarine"
    ],
    "displayedValueProcessingKind": "DecimalRoundedPercentage",
    "valueProcessingKind": "Multiplier"
  },
  {
    "name": "ConsumablesWorkTime",
    "value": 1.1,
    "gameLocalizationKey": "PARAMS_MODIFIER_CONSUMABLESWORKTIME",
    "appLocalizationKey": null,
    "unit": "Percent",
    "affectedProperties": [
      "ConsumableDataContainer.WorkTime.Ship"
    ],
    "displayedValueProcessingKind": "DecimalRoundedPercentage",
    "valueProcessingKind": "Multiplier"
  },
  {
    "name": "crashCrewAdditionalConsumables",
    "value": 1,
    "gameLocalizationKey": "PARAMS_MODIFIER_CRASHCREWADDITIONALCONSUMABLES",
    "appLocalizationKey": null,
    "unit": "None",
    "affectedProperties": [
      "ConsumableDataContainer.Uses.PCY009.PCY037"
    ],
    "displayedValueProcessingKind": "ToInt",
    "valueProcessingKind": "DirectAdd"
  },
  {
    "name": "crashCrewReloadCoeff",
    "value": 0.97,
    "gameLocalizationKey": "PARAMS_MODIFIER_CRASHCREWRELOADCOEFF_SKILL",
    "appLocalizationKey": null,
    "unit": "Percent",
    "affectedProperties": [
      "ConsumableDataContainer.Reload.PCY009.PCY037"
    ],
    "displayedValueProcessingKind": "DecimalRoundedPercentage",
    "valueProcessingKind": "Multiplier"
  },
  {
    "name": "crashCrewWorkTimeCoeff",
    "value": 1.1,
    "gameLocalizationKey": "PARAMS_MODIFIER_CRASHCREWWORKTIMECOEFF_SKILL",
    "appLocalizationKey": null,
    "unit": "Percent",
    "affectedProperties": [
      "ConsumableDataContainer.WorkTime.PCY009.PCY037"
    ],
    "displayedValueProcessingKind": "DecimalRoundedPercentage",
    "valueProcessingKind": "Multiplier"
  },
  {
    "name": "critProbCoefficient",
    "value": 0.7,
    "gameLocalizationKey": "PARAMS_MODIFIER_CRITPROBCOEFFICIENT",
    "appLocalizationKey": null,
    "unit": "Percent",
    "affectedProperties": [],
    "displayedValueProcessingKind": "DecimalRoundedPercentage",
    "valueProcessingKind": "None"
  },
  {
    "name": "damagedEngineCoeff",
    "value": 0.2167,
    "gameLocalizationKey": "PARAMS_MODIFIER_DAMAGEDENGINECOEFF",
    "appLocalizationKey": null,
    "unit": "Percent",
    "affectedProperties": [],
    "displayedValueProcessingKind": "DecimalRoundedPercentage",
    "valueProcessingKind": "None"
  },
  {
    "name": "dcAlphaDamageMultiplier",
    "value": 1.1,
    "gameLocalizationKey": "PARAMS_MODIFIER_DCALPHADAMAGEMULTIPLIER_DESTROYER",
    "appLocalizationKey": null,
    "unit": "Percent",
    "affectedProperties": [
      "DepthChargeDataContainer.Damage"
    ],
    "displayedValueProcessingKind": "DecimalRoundedPercentage",
    "valueProcessingKind": "Multiplier"
  },
  {
    "name": "dcAlphaDamageMultiplier_AirCarrier",
    "value": 1,
    "gameLocalizationKey": "PARAMS_MODIFIER_DCALPHADAMAGEMULTIPLIER_AIRCARRIER",
    "appLocalizationKey": null,
    "unit": "Percent",
    "affectedProperties": [
      "DepthChargeDataContainer.Damage"
    ],
    "displayedValueProcessingKind": "DecimalRoundedPercentage",
    "valueProcessingKind": "Multiplier"
  },
  {
    "name": "dcAlphaDamageMultiplier_Battleship",
    "value": 1.1,
    "gameLocalizationKey": "PARAMS_MODIFIER_DCALPHADAMAGEMULTIPLIER_BATTLESHIP",
    "appLocalizationKey": null,
    "unit": "Percent",
    "affectedProperties": [
      "DepthChargeDataContainer.Damage"
    ],
    "displayedValueProcessingKind": "DecimalRoundedPercentage",
    "valueProcessingKind": "Multiplier"
  },
  {
    "name": "dcAlphaDamageMultiplier_Cruiser",
    "value": 1.15,
    "gameLocalizationKey": "PARAMS_MODIFIER_DCALPHADAMAGEMULTIPLIER_CRUISER",
    "appLocalizationKey": null,
    "unit": "Percent",
    "affectedProperties": [
      "DepthChargeDataContainer.Damage"
    ],
    "displayedValueProcessingKind": "DecimalRoundedPercentage",
    "valueProcessingKind": "Multiplier"
  },
  {
    "name": "dcAlphaDamageMultiplier_Destroyer",
    "value": 1,
    "gameLocalizationKey": "PARAMS_MODIFIER_DCALPHADAMAGEMULTIPLIER_DESTROYER",
    "appLocalizationKey": null,
    "unit": "Percent",
    "affectedProperties": [
      "DepthChargeDataContainer.Damage"
    ],
    "displayedValueProcessingKind": "DecimalRoundedPercentage",
    "valueProcessingKind": "Multiplier"
  },
  {
    "name": "dcAlphaDamageMultiplier_Submarine",
    "value": 1,
    "gameLocalizationKey": "PARAMS_MODIFIER_DCALPHADAMAGEMULTIPLIER_SUBMARINE",
    "appLocalizationKey": null,
    "unit": "Percent",
    "affectedProperties": [
      "DepthChargeDataContainer.Damage"
    ],
    "displayedValueProcessingKind": "DecimalRoundedPercentage",
    "valueProcessingKind": "Multiplier"
  },
  {
    "name": "dcNumPacksBonus",
    "value": 2,
    "gameLocalizationKey": "PARAMS_MODIFIER_DCNUMPACKSBONUS",
    "appLocalizationKey": null,
    "unit": "None",
    "affectedProperties": [
      "DepthChargesLauncherDataContainer.NumberOfUses"
    ],
    "displayedValueProcessingKind": "ToInt",
    "valueProcessingKind": "DirectAdd"
  },
  {
    "name": "dcSplashRadiusMultiplier",
    "value": 1.15,
    "gameLocalizationKey": "PARAMS_MODIFIER_DCSPLASHRADIUSMULTIPLIER",
    "appLocalizationKey": null,
    "unit": "Percent",
    "affectedProperties": [
      "ShellDataContainer.UnderwaterSplash"
    ],
    "displayedValueProcessingKind": "DecimalRoundedPercentage",
    "valueProcessingKind": "Multiplier"
  },
  {
    "name": "distanceToKill",
    "value": 35,
    "gameLocalizationKey": "",
    "appLocalizationKey": null,
    "unit": "None",
    "affectedProperties": [],
    "displayedValueProcessingKind": "ToInt",
    "valueProcessingKind": "None"
  },
  {
    "name": "distShip",
    "value": 164,
    "gameLocalizationKey": "PARAMS_MODIFIER_DISTSHIP",
    "appLocalizationKey": null,
    "unit": "KM",
    "affectedProperties": [],
    "displayedValueProcessingKind": "BigWorldToKmDecimal",
    "valueProcessingKind": "None"
  },
  {
    "name": "distTorpedo",
    "value": 114,
    "gameLocalizationKey": "PARAMS_MODIFIER_DISTTORPEDO",
    "appLocalizationKey": null,
    "unit": "KM",
    "affectedProperties": [],
    "displayedValueProcessingKind": "BigWorldToKmDecimal",
    "valueProcessingKind": "None"
  },
  {
    "name": "diveBomberAccuracyIncRateCoeff",
    "value": 1.075,
    "gameLocalizationKey": "PARAMS_MODIFIER_DIVEBOMBERACCURACYINCRATECOEFF",
    "appLocalizationKey": null,
    "unit": "Percent",
    "affectedProperties": [
      "CvAircraftDataContainer.AimRate.DiveBomber"
    ],
    "displayedValueProcessingKind": "DecimalRoundedPercentage",
    "valueProcessingKind": "Multiplier"
  },
  {
    "name": "diveBomberHealth",
    "value": 1.075,
    "gameLocalizationKey": "PARAMS_MODIFIER_DIVEBOMBERHEALTH",
    "appLocalizationKey": null,
    "unit": "Percent",
    "affectedProperties": [
      "CvAircraftDataContainer.Hp.DiveBomber"
    ],
    "displayedValueProcessingKind": "DecimalRoundedPercentage",
    "valueProcessingKind": "Multiplier"
  },
  {
    "name": "diveBomberMaxSpeedMultiplier",
    "value": 0.9899,
    "gameLocalizationKey": "PARAMS_MODIFIER_DIVEBOMBERMAXSPEEDMULTIPLIER",
    "appLocalizationKey": null,
    "unit": "Percent",
    "affectedProperties": [
      "CvAircraftDataContainer.MaxSpeed.DiveBomber"
    ],
    "displayedValueProcessingKind": "DecimalRoundedPercentage",
    "valueProcessingKind": "Multiplier"
  },
  {
    "name": "diveBomberMinSpeedMultiplier",
    "value": 1.0142,
    "gameLocalizationKey": "PARAMS_MODIFIER_DIVEBOMBERMINSPEEDMULTIPLIER",
    "appLocalizationKey": null,
    "unit": "Percent",
    "affectedProperties": [
      "CvAircraftDataContainer.MinSpeed.DiveBomber"
    ],
    "displayedValueProcessingKind": "DecimalRoundedPercentage",
    "valueProcessingKind": "Multiplier"
  },
  {
    "name": "diveBomberSpeedMultiplier",
    "value": 1.05,
    "gameLocalizationKey": "PARAMS_MODIFIER_DIVEBOMBERSPEEDMULTIPLIER",
    "appLocalizationKey": null,
    "unit": "Percent",
    "affectedProperties": [
      "CvAircraftDataContainer.CruisingSpeed.DiveBomber"
    ],
    "displayedValueProcessingKind": "DecimalRoundedPercentage",
    "valueProcessingKind": "Multiplier"
  },
  {
    "name": "dogFightTime",
    "value": 5,
    "gameLocalizationKey": "",
    "appLocalizationKey": null,
    "unit": "None",
    "affectedProperties": [],
    "displayedValueProcessingKind": "ToInt",
    "valueProcessingKind": "None"
  },
  {
    "name": "engineBackwardForsageMaxSpeed",
    "value": 2,
    "gameLocalizationKey": "",
    "appLocalizationKey": null,
    "unit": "Percent",
    "affectedProperties": [
      "ManeuverabilityDataContainer.EngineBackwardForsageMaxSpeed"
    ],
    "displayedValueProcessingKind": "DecimalRoundedPercentage",
    "valueProcessingKind": "Multiplier"
  },
  {
    "name": "engineBackwardForsagePower",
    "value": 1.15,
    "gameLocalizationKey": "",
    "appLocalizationKey": null,
    "unit": "None",
    "affectedProperties": [
      "ManeuverabilityDataContainer.EngineBackwardForsagePower"
    ],
    "displayedValueProcessingKind": "ToInt",
    "valueProcessingKind": "Multiplier"
  },
  {
    "name": "engineBackwardUpTime",
    "value": 0.5,
    "gameLocalizationKey": "",
    "appLocalizationKey": null,
    "unit": "Percent",
    "affectedProperties": [
      "ManeuverabilityDataContainer.EngineBackwardUpTime"
    ],
    "displayedValueProcessingKind": "DecimalRoundedPercentage",
    "valueProcessingKind": "Multiplier"
  },
  {
    "name": "engineCritProb",
    "value": 0.8,
    "gameLocalizationKey": "PARAMS_MODIFIER_ENGINECRITPROB",
    "appLocalizationKey": null,
    "unit": "Percent",
    "affectedProperties": [],
    "displayedValueProcessingKind": "DecimalRoundedPercentage",
    "valueProcessingKind": "None"
  },
  {
    "name": "engineForwardForsageMaxSpeed",
    "value": 3.75,
    "gameLocalizationKey": "",
    "appLocalizationKey": null,
    "unit": "Percent",
    "affectedProperties": [
      "ManeuverabilityDataContainer.EngineForwardForsageMaxSpeed"
    ],
    "displayedValueProcessingKind": "DecimalRoundedPercentage",
    "valueProcessingKind": "Multiplier"
  },
  {
    "name": "engineForwardForsagePower",
    "value": 1.1,
    "gameLocalizationKey": "",
    "appLocalizationKey": null,
    "unit": "None",
    "affectedProperties": [
      "ManeuverabilityDataContainer.EngineForwardForsagePower"
    ],
    "displayedValueProcessingKind": "ToInt",
    "valueProcessingKind": "Multiplier"
  },
  {
    "name": "engineForwardUpTime",
    "value": 0.5,
    "gameLocalizationKey": "PARAMS_MODIFIER_ENGINEFORWARDUPTIME",
    "appLocalizationKey": null,
    "unit": "Percent",
    "affectedProperties": [
      "ManeuverabilityDataContainer.EngineForwardUpTime"
    ],
    "displayedValueProcessingKind": "DecimalRoundedPercentage",
    "valueProcessingKind": "Multiplier"
  },
  {
    "name": "engineRepairTime",
    "value": 0.8,
    "gameLocalizationKey": "PARAMS_MODIFIER_ENGINEREPAIRTIME",
    "appLocalizationKey": null,
    "unit": "Percent",
    "affectedProperties": [],
    "displayedValueProcessingKind": "DecimalRoundedPercentage",
    "valueProcessingKind": "None"
  },
  {
    "name": "exterior_planeRegenerationRate",
    "value": 1.05,
    "gameLocalizationKey": "PARAMS_MODIFIER_PLANEREGENERATIONRATE",
    "appLocalizationKey": null,
    "unit": "Percent",
    "affectedProperties": [],
    "displayedValueProcessingKind": "PositivePercentage",
    "valueProcessingKind": "None"
  },
  {
    "name": "exterior_regenerationHPSpeed",
    "value": 1.2,
    "gameLocalizationKey": "PARAMS_MODIFIER_REGENERATIONHPSPEED_PERCENT",
    "appLocalizationKey": null,
    "unit": "Percent",
    "affectedProperties": ["ConsumableDataContainer.RegenerationHpSpeed.PCY010"],
    "displayedValueProcessingKind": "PositivePercentage",
    "valueProcessingKind": "Multiplier"
  },
  {
    "name": "extraFighterCount",
    "value": 1,
    "gameLocalizationKey": "PARAMS_MODIFIER_EXTRAFIGHTERCOUNT",
    "appLocalizationKey": null,
    "unit": "None",
    "affectedProperties": [
      "ConsumableDataContainer.ExtraFighters.PCY012.PCY03"
    ],
    "displayedValueProcessingKind": "ToInt",
    "valueProcessingKind": "DirectAdd"
  },
  {
    "name": "fighterAccuracyIncRateCoeff",
    "value": 1.075,
    "gameLocalizationKey": "PARAMS_MODIFIER_FIGHTERACCURACYINCRATECOEFF",
    "appLocalizationKey": null,
    "unit": "Percent",
    "affectedProperties": [
      "CvAircraftDataContainer.AimRate.Rocket"
    ],
    "displayedValueProcessingKind": "DecimalRoundedPercentage",
    "valueProcessingKind": "Multiplier"
  },
  {
    "name": "fighterAimingTime",
    "value": 2,
    "gameLocalizationKey": "PARAMS_MODIFIER_FIGHTERAIMINGTIME",
    "appLocalizationKey": null,
    "unit": "S",
    "affectedProperties": [
      "CvAircraftDataContainer.AimingTime.Rocket"
    ],
    "displayedValueProcessingKind": "None",
    "valueProcessingKind": "DirectAdd"
  },
  {
    "name": "fighterHealth",
    "value": 1.075,
    "gameLocalizationKey": "PARAMS_MODIFIER_FIGHTERHEALTH",
    "appLocalizationKey": null,
    "unit": "Percent",
    "affectedProperties": [
      "CvAircraftDataContainer.Hp.Rocket"
    ],
    "displayedValueProcessingKind": "DecimalRoundedPercentage",
    "valueProcessingKind": "Multiplier"
  },
  {
    "name": "fightersNum",
    "value": 4,
    "gameLocalizationKey": "PARAMS_MODIFIER_FIGHTERSNUM",
    "appLocalizationKey": null,
    "unit": "None",
    "affectedProperties": [],
    "displayedValueProcessingKind": "None",
    "valueProcessingKind": "None"
  },
  {
    "name": "firstSectorTimeCoeff",
    "value": 1.25,
    "gameLocalizationKey": "PARAMS_MODIFIER_FIRSTSECTORTIMECOEFF",
    "appLocalizationKey": null,
    "unit": "Percent",
    "affectedProperties": [
      "PingerGunDataContainer.PingDuration.First"
    ],
    "displayedValueProcessingKind": "DecimalRoundedPercentage",
    "valueProcessingKind": "Multiplier"
  },
  {
    "name": "floodChanceFactor",
    "value": 1.3,
    "gameLocalizationKey": "PARAMS_MODIFIER_FLOODCHANCEFACTOR",
    "appLocalizationKey": null,
    "unit": "Percent",
    "affectedProperties": [
      "TorpedoDataContainer.FloodChance.Ship"
    ],
    "displayedValueProcessingKind": "DecimalRoundedPercentage",
    "valueProcessingKind": "Multiplier"
  },
  {
    "name": "floodChanceFactorPlane",
    "value": 1.15,
    "gameLocalizationKey": "PARAMS_MODIFIER_FLOODCHANCEFACTORPLANE",
    "appLocalizationKey": null,
    "unit": "Percent",
    "affectedProperties": [
      "TorpedoDataContainer.FloodChance.Plane"
    ],
    "displayedValueProcessingKind": "DecimalRoundedPercentage",
    "valueProcessingKind": "Multiplier"
  },
  {
    "name": "floodProb",
    "value": 0.97,
    "gameLocalizationKey": "PARAMS_MODIFIER_FLOODPROB",
    "appLocalizationKey": null,
    "unit": "Percent",
    "affectedProperties": ["SurvivabilityDataContainer.FloodChanceResistance"],
    "displayedValueProcessingKind": "DecimalRoundedPercentage",
    "valueProcessingKind": "Multiplier"
  },
  {
    "name": "floodTime",
    "value": 1.25,
    "gameLocalizationKey": "PARAMS_MODIFIER_FLOODTIME",
    "appLocalizationKey": null,
    "unit": "Percent",
    "affectedProperties": [
      "SurvivabilityDataContainer.FloodDuration"
    ],
    "displayedValueProcessingKind": "DecimalRoundedPercentage",
    "valueProcessingKind": "Multiplier"
  },
  {
    "name": "flyAwayTime",
    "value": 6,
    "gameLocalizationKey": null,
    "appLocalizationKey": "ShipStats_FlyAwayTime",
    "unit": "S",
    "affectedProperties": [],
    "displayedValueProcessingKind": "None",
    "valueProcessingKind": "None"
  },
  {
    "name": "forwardEngineForsag",
    "value": 2.5,
    "gameLocalizationKey": "",
    "appLocalizationKey": null,
    "unit": "Percent",
    "affectedProperties": [
      "ManeuverabilityDataContainer.ForwardEngineForsag.SpeedBoost"
    ],
    "displayedValueProcessingKind": "DecimalRoundedPercentage",
    "valueProcessingKind": "DirectAdd"
  },
  {
    "name": "forwardEngineForsagMaxSpeed",
    "value": 10,
    "gameLocalizationKey": "",
    "appLocalizationKey": null,
    "unit": "None",
    "affectedProperties": [
      "ManeuverabilityDataContainer.ForwardEngineForsagMaxSpeed"
    ],
    "displayedValueProcessingKind": "ToInt",
    "valueProcessingKind": "DirectAdd"
  },
  {
    "name": "GMAPDamageCoeff",
    "value": 1.075,
    "gameLocalizationKey": "PARAMS_MODIFIER_GMAPDAMAGECOEFF",
    "appLocalizationKey": null,
    "unit": "Percent",
    "affectedProperties": [
      "ShellDataContainer.Damage.Ap"
    ],
    "displayedValueProcessingKind": "DecimalRoundedPercentage",
    "valueProcessingKind": "Multiplier"
  },
  {
    "name": "GMBigGunVisibilityCoeff",
    "value": 1.15,
    "gameLocalizationKey": "PARAMS_MODIFIER_GMBIGGUNVISIBILITYCOEFF",
    "appLocalizationKey": null,
    "unit": "Percent",
    "affectedProperties": [
      "ConcealmentDataContainer.Visibility.Big"
    ],
    "displayedValueProcessingKind": "DecimalRoundedPercentage",
    "valueProcessingKind": "Multiplier"
  },
  {
    "name": "GMCritProb",
    "value": 0.8,
    "gameLocalizationKey": "PARAMS_MODIFIER_GMCRITPROB",
    "appLocalizationKey": null,
    "unit": "Percent",
    "affectedProperties": [],
    "displayedValueProcessingKind": "DecimalRoundedPercentage",
    "valueProcessingKind": "None"
  },
  {
    "name": "GMDamageCoeff",
    "value": 1.5,
    "gameLocalizationKey": "PARAMS_MODIFIER_GMDAMAGECOEFF",
    "appLocalizationKey": null,
    "unit": "Percent",
    "affectedProperties": ["ShellDataContainer.Damage.Ap",
      "ShellDataContainer.Damage.HESAP"],
    "displayedValueProcessingKind": "DecimalRoundedPercentage",
    "valueProcessingKind": "Multiplier"
  },
  {
    "name": "GMHeavyCruiserCaliberDamageCoeff",
    "value": 1.05,
    "gameLocalizationKey": "PARAMS_MODIFIER_GMHEAVYCRUISERCALIBERDAMAGECOEFF",
    "appLocalizationKey": null,
    "unit": "Percent",
    "affectedProperties": [
      "ShellDataContainer.Damage.BigAp"
    ],
    "displayedValueProcessingKind": "DecimalRoundedPercentage",
    "valueProcessingKind": "Multiplier"
  },
  {
    "name": "GMHECSDamageCoeff",
    "value": 1.1,
    "gameLocalizationKey": "PARAMS_MODIFIER_GMHECSDAMAGECOEFF",
    "appLocalizationKey": null,
    "unit": "Percent",
    "affectedProperties": [
      "ShellDataContainer.Damage.HESAP"
    ],
    "displayedValueProcessingKind": "DecimalRoundedPercentage",
    "valueProcessingKind": "Multiplier"
  },
  {
    "name": "GMIdealRadius",
    "value": 0.65,
    "gameLocalizationKey": "PARAMS_MODIFIER_GMIDEALRADIUS",
    "appLocalizationKey": null,
    "unit": "Percent",
    "affectedProperties": [
      "MainBatteryDataContainer.Dispersion.IdealRadius"
    ],
    "displayedValueProcessingKind": "DecimalRoundedPercentage",
    "valueProcessingKind": "Multiplier"
  },
  {
    "name": "GMMaxDist",
    "value": 1.08,
    "gameLocalizationKey": "PARAMS_MODIFIER_GMMAXDIST",
    "appLocalizationKey": null,
    "unit": "Percent",
    "affectedProperties": [
      "MainBatteryDataContainer.Range"
    ],
    "displayedValueProcessingKind": "DecimalRoundedPercentage",
    "valueProcessingKind": "Multiplier"
  },
  {
    "name": "GMMaxHP",
    "value": 1.5,
    "gameLocalizationKey": "PARAMS_MODIFIER_GMMAXHP",
    "appLocalizationKey": null,
    "unit": "Percent",
    "affectedProperties": [],
    "displayedValueProcessingKind": "DecimalRoundedPercentage",
    "valueProcessingKind": "None"
  },
  {
    "name": "GMPenetrationCoeffHE",
    "value": 1.25,
    "gameLocalizationKey": "PARAMS_MODIFIER_GMPENETRATIONCOEFFHE",
    "appLocalizationKey": null,
    "unit": "Percent",
    "affectedProperties": [
      "ShellDataContainer.Penetration.Primary"
    ],
    "displayedValueProcessingKind": "DecimalRoundedPercentage",
    "valueProcessingKind": "Multiplier"
  },
  {
    "name": "GMRepairTime",
    "value": 0.8,
    "gameLocalizationKey": "PARAMS_MODIFIER_GMREPAIRTIME",
    "appLocalizationKey": null,
    "unit": "Percent",
    "affectedProperties": [],
    "displayedValueProcessingKind": "DecimalRoundedPercentage",
    "valueProcessingKind": "None"
  },
  {
    "name": "GMRotationSpeed",
    "value": 0.93,
    "gameLocalizationKey": "PARAMS_MODIFIER_GMROTATIONSPEED_DESTROYER",
    "appLocalizationKey": null,
    "unit": "Percent",
    "affectedProperties": [
      "MainBatteryDataContainer.TraverseSpeed"
    ],
    "displayedValueProcessingKind": "DecimalRoundedPercentage",
    "valueProcessingKind": "Multiplier"
  },
  {
    "name": "GMRotationSpeed_AirCarrier",
    "value": 1,
    "gameLocalizationKey": "",
    "appLocalizationKey": null,
    "unit": "Percent",
    "affectedProperties": [
      "MainBatteryDataContainer.TraverseSpeed"
    ],
    "displayedValueProcessingKind": "ToInt",
    "valueProcessingKind": "Multiplier"
  },
  {
    "name": "GMRotationSpeed_Battleship",
    "value": 1.2,
    "gameLocalizationKey": "PARAMS_MODIFIER_GMROTATIONSPEED_BATTLESHIP",
    "appLocalizationKey": null,
    "unit": "Percent",
    "affectedProperties": [
      "MainBatteryDataContainer.TraverseSpeed"
    ],
    "displayedValueProcessingKind": "DecimalRoundedPercentage",
    "valueProcessingKind": "Multiplier"
  },
  {
    "name": "GMRotationSpeed_Cruiser",
    "value": 1.15,
    "gameLocalizationKey": "PARAMS_MODIFIER_GMROTATIONSPEED_CRUISER",
    "appLocalizationKey": null,
    "unit": "Percent",
    "affectedProperties": [
      "MainBatteryDataContainer.TraverseSpeed"
    ],
    "displayedValueProcessingKind": "DecimalRoundedPercentage",
    "valueProcessingKind": "Multiplier"
  },
  {
    "name": "GMRotationSpeed_Destroyer",
    "value": 1.15,
    "gameLocalizationKey": "PARAMS_MODIFIER_GMROTATIONSPEED_DESTROYER",
    "appLocalizationKey": null,
    "unit": "Percent",
    "affectedProperties": [
      "MainBatteryDataContainer.TraverseSpeed"
    ],
    "displayedValueProcessingKind": "DecimalRoundedPercentage",
    "valueProcessingKind": "Multiplier"
  },
  {
    "name": "GMRotationSpeed_Submarine",
    "value": 1,
    "gameLocalizationKey": "PARAMS_MODIFIER_GMROTATIONSPEED_SUBMARINE",
    "appLocalizationKey": null,
    "unit": "Percent",
    "affectedProperties": [
      "MainBatteryDataContainer.TraverseSpeed"
    ],
    "displayedValueProcessingKind": "ToInt",
    "valueProcessingKind": "Multiplier"
  },
  {
    "name": "GMShotDelay",
    "value": 0.85,
    "gameLocalizationKey": "PARAMS_MODIFIER_GMSHOTDELAY",
    "appLocalizationKey": null,
    "unit": "Percent",
    "affectedProperties": [
      "MainBatteryDataContainer.Reload"
    ],
    "displayedValueProcessingKind": "DecimalRoundedPercentage",
    "valueProcessingKind": "Multiplier"
  },
  {
    "name": "GSIdealRadius",
    "value": 0.9,
    "gameLocalizationKey": "PARAMS_MODIFIER_GSIDEALRADIUS",
    "appLocalizationKey": null,
    "unit": "Percent",
    "affectedProperties": [
      "SecondaryBatteryDataContainer.Dispersion.IdealRadius"
    ],
    "displayedValueProcessingKind": "DecimalRoundedPercentage",
    "valueProcessingKind": "Multiplier"
  },
  {
    "name": "GSMaxDist",
    "value": 1.2,
    "gameLocalizationKey": "PARAMS_MODIFIER_GSMAXDIST",
    "appLocalizationKey": null,
    "unit": "Percent",
    "affectedProperties": [
      "SecondaryBatteryDataContainer.Range"
    ],
    "displayedValueProcessingKind": "DecimalRoundedPercentage",
    "valueProcessingKind": "Multiplier"
  },
  {
    "name": "GSMaxHP",
    "value": 2,
    "gameLocalizationKey": "PARAMS_MODIFIER_GSMAXHP_DESTROYER",
    "appLocalizationKey": null,
    "unit": "Percent",
    "affectedProperties": [],
    "displayedValueProcessingKind": "VariablePercentage",
    "valueProcessingKind": "None"
  },
  {
    "name": "GSMaxHP_AirCarrier",
    "value": 1,
    "gameLocalizationKey": "PARAMS_MODIFIER_GSMAXHP_AIRCARRIER",
    "appLocalizationKey": null,
    "unit": "Percent",
    "affectedProperties": [],
    "displayedValueProcessingKind": "VariablePercentage",
    "valueProcessingKind": "None"
  },
  {
    "name": "GSMaxHP_Battleship",
    "value": 1.15,
    "gameLocalizationKey": "PARAMS_MODIFIER_GSMAXHP_BATTLESHIP",
    "appLocalizationKey": null,
    "unit": "Percent",
    "affectedProperties": [],
    "displayedValueProcessingKind": "VariablePercentage",
    "valueProcessingKind": "None"
  },
  {
    "name": "GSMaxHP_Cruiser",
    "value": 1,
    "gameLocalizationKey": "PARAMS_MODIFIER_GSMAXHP_CRUISER",
    "appLocalizationKey": null,
    "unit": "Percent",
    "affectedProperties": [],
    "displayedValueProcessingKind": "VariablePercentage",
    "valueProcessingKind": "None"
  },
  {
    "name": "GSMaxHP_Destroyer",
    "value": 1.15,
    "gameLocalizationKey": "PARAMS_MODIFIER_GSMAXHP_DESTROYER",
    "appLocalizationKey": null,
    "unit": "Percent",
    "affectedProperties": [],
    "displayedValueProcessingKind": "VariablePercentage",
    "valueProcessingKind": "None"
  },
  {
    "name": "GSMaxHP_Submarine",
    "value": 1,
    "gameLocalizationKey": "PARAMS_MODIFIER_GSMAXHP_SUBMARINE",
    "appLocalizationKey": null,
    "unit": "Percent",
    "affectedProperties": [],
    "displayedValueProcessingKind": "VariablePercentage",
    "valueProcessingKind": "None"
  },
  {
    "name": "GSPenetrationCoeffHE",
    "value": 1.25,
    "gameLocalizationKey": "PARAMS_MODIFIER_GSPENETRATIONCOEFFHE",
    "appLocalizationKey": null,
    "unit": "Percent",
    "affectedProperties": [
      "ShellDataContainer.Penetration.Secondary"
    ],
    "displayedValueProcessingKind": "DecimalRoundedPercentage",
    "valueProcessingKind": "Multiplier"
  },
  {
    "name": "GSPriorityTargetIdealRadius",
    "value": 0.5,
    "gameLocalizationKey": "PARAMS_MODIFIER_GSPRIORITYTARGETIDEALRADIUS",
    "appLocalizationKey": null,
    "unit": "Percent",
    "affectedProperties": [],
    "displayedValueProcessingKind": "DecimalRoundedPercentage",
    "valueProcessingKind": "None"
  },
  {
    "name": "GSShotDelay",
    "value": 0.9,
    "gameLocalizationKey": "PARAMS_MODIFIER_GSSHOTDELAY",
    "appLocalizationKey": null,
    "unit": "Percent",
    "affectedProperties": [
      "SecondaryBatteryDataContainer.Reload"
    ],
    "displayedValueProcessingKind": "DecimalRoundedPercentage",
    "valueProcessingKind": "Multiplier"
  },
  {
    "name": "GTCritProb",
    "value": 1.5,
    "gameLocalizationKey": "PARAMS_MODIFIER_GTCRITPROB",
    "appLocalizationKey": null,
    "unit": "Percent",
    "affectedProperties": [],
    "displayedValueProcessingKind": "DecimalRoundedPercentage",
    "valueProcessingKind": "None"
  },
  {
    "name": "GTMaxHP",
    "value": 1.5,
    "gameLocalizationKey": "PARAMS_MODIFIER_GTMAXHP",
    "appLocalizationKey": null,
    "unit": "Percent",
    "affectedProperties": [],
    "displayedValueProcessingKind": "DecimalRoundedPercentage",
    "valueProcessingKind": "None"
  },
  {
    "name": "GTRepairTime",
    "value": 0.8,
    "gameLocalizationKey": "PARAMS_MODIFIER_GTREPAIRTIME",
    "appLocalizationKey": null,
    "unit": "Percent",
    "affectedProperties": [],
    "displayedValueProcessingKind": "DecimalRoundedPercentage",
    "valueProcessingKind": "None"
  },
  {
    "name": "GTRotationSpeed",
    "value": 1.2,
    "gameLocalizationKey": "PARAMS_MODIFIER_GTROTATIONSPEED",
    "appLocalizationKey": null,
    "unit": "Percent",
    "affectedProperties": [
      "TorpedoArmamentDataContainer.TraverseSpeed"
    ],
    "displayedValueProcessingKind": "DecimalRoundedPercentage",
    "valueProcessingKind": "Multiplier"
  },
  {
    "name": "GTShotDelay",
    "value": 0.85,
    "gameLocalizationKey": "PARAMS_MODIFIER_GTSHOTDELAY",
    "appLocalizationKey": null,
    "unit": "Percent",
    "affectedProperties": [
      "TorpedoArmamentDataContainer.Reload"
    ],
    "displayedValueProcessingKind": "DecimalRoundedPercentage",
    "valueProcessingKind": "Multiplier"
  },
  {
    "name": "healForsageReloadCoeff",
    "value": 0.8,
    "gameLocalizationKey": "PARAMS_MODIFIER_HEALFORSAGERELOADCOEFF_SKILL",
    "appLocalizationKey": null,
    "unit": "Percent",
    "affectedProperties": [
      "ConsumableDataContainer.PCY035.Reload"
    ],
    "displayedValueProcessingKind": "DecimalRoundedPercentage",
    "valueProcessingKind": "Multiplier"
  },
  {
    "name": "healthPerLevel_AirCarrier",
    "value": 0,
    "gameLocalizationKey": "",
    "appLocalizationKey": null,
    "unit": "HP",
    "affectedProperties": [
      "SurvivabilityDataContainer.Hp"
    ],
    "displayedValueProcessingKind": "ToInt",
    "valueProcessingKind": "Multiplier"
  },
  {
    "name": "healthPerLevel_Battleship",
    "value": 0,
    "gameLocalizationKey": "",
    "appLocalizationKey": null,
    "unit": "HP",
    "affectedProperties": [
      "SurvivabilityDataContainer.Hp"
    ],
    "displayedValueProcessingKind": "ToInt",
    "valueProcessingKind": "Multiplier"
  },
  {
    "name": "healthPerLevel_Cruiser",
    "value": 450,
    "gameLocalizationKey": "PARAMS_MODIFIER_HEALTHPERLEVEL_CRUISER",
    "appLocalizationKey": null,
    "unit": "HP",
    "affectedProperties": [
      "SurvivabilityDataContainer.Hp"
    ],
    "displayedValueProcessingKind": "ToInt",
    "valueProcessingKind": "Multiplier"
  },
  {
    "name": "healthPerLevel_Destroyer",
    "value": 350,
    "gameLocalizationKey": "PARAMS_MODIFIER_HEALTHPERLEVEL_DESTROYER",
    "appLocalizationKey": null,
    "unit": "HP",
    "affectedProperties": [
      "SurvivabilityDataContainer.Hp"
    ],
    "displayedValueProcessingKind": "ToInt",
    "valueProcessingKind": "Multiplier"
  },
  {
    "name": "healthPerLevel_Submarine",
    "value": 0,
    "gameLocalizationKey": "",
    "appLocalizationKey": null,
    "unit": "HP",
    "affectedProperties": [
      "SurvivabilityDataContainer.Hp"
    ],
    "displayedValueProcessingKind": "ToInt",
    "valueProcessingKind": "Multiplier"
  },
  {
    "name": "height",
    "value": 5,
    "gameLocalizationKey": "",
    "appLocalizationKey": null,
    "unit": "None",
    "affectedProperties": [],
    "displayedValueProcessingKind": "ToInt",
    "valueProcessingKind": "None"
  },
  {
    "name": "hlCritTimeCoeff",
    "value": 0.85,
    "gameLocalizationKey": "PARAMS_MODIFIER_HLCRITTIMECOEFF",
    "appLocalizationKey": null,
    "unit": "Percent",
    "affectedProperties": [
      "SurvivabilityDataContainer.FireDuration",
      "SurvivabilityDataContainer.FloodDuration"
    ],
    "displayedValueProcessingKind": "DecimalRoundedPercentage",
    "valueProcessingKind": "Multiplier"
  },
  {
    "name": "hydrophoneUpdateFrequency",
    "value": 6,
    "gameLocalizationKey": "PARAMS_MODIFIER_HYDROPHONEUPDATEFREQUENCY",
    "appLocalizationKey": null,
    "unit": "S",
    "affectedProperties": [],
    "displayedValueProcessingKind": "None",
    "valueProcessingKind": "None"
  },
  {
    "name": "hydrophoneUpdateFrequencyCoeff",
    "value": 0.8,
    "gameLocalizationKey": "PARAMS_MODIFIER_HYDROPHONEUPDATEFREQUENCYCOEFF",
    "appLocalizationKey": null,
    "unit": "Percent",
    "affectedProperties": [
      "ConsumableDataContainer.HydrophoneUpdateFrequency.PCY045"
    ],
    "displayedValueProcessingKind": "DecimalRoundedPercentage",
    "valueProcessingKind": "Multiplier"
  },
  {
    "name": "hydrophoneWaveRadius",
    "value": 8000,
    "gameLocalizationKey": "PARAMS_MODIFIER_HYDROPHONEWAVERADIUS",
    "appLocalizationKey": null,
    "unit": "KM",
    "affectedProperties": [],
    "displayedValueProcessingKind": "MeterToKm",
    "valueProcessingKind": "None"
  },
  {
    "name": "hydrophoneWaveSpeedCoeff",
    "value": 1,
    "gameLocalizationKey": "",
    "appLocalizationKey": null,
    "unit": "None",
    "affectedProperties": [],
    "displayedValueProcessingKind": "ToInt",
    "valueProcessingKind": "None"
  },
  {
    "name": "ignorePTZBonus",
    "value": 10,
    "gameLocalizationKey": "PARAMS_MODIFIER_IGNOREPTZBONUS",
    "appLocalizationKey": null,
    "unit": "Percent",
    "affectedProperties": [],
    "displayedValueProcessingKind": "ToInt",
    "valueProcessingKind": "None"
  },
  {
    "name": "invisible_airDefenseDispReloadCoeff",
    "value": 0.925,
    "gameLocalizationKey": "",
    "appLocalizationKey": null,
    "unit": "Percent",
    "affectedProperties": [
      "ConsumableDataContainer.Reload.PCY011"
    ],
    "displayedValueProcessingKind": "DecimalRoundedPercentage",
    "valueProcessingKind": "Multiplier"
  },
  {
    "name": "invisible_artilleryBoostersReloadCoeff",
    "value": 0.925,
    "gameLocalizationKey": "",
    "appLocalizationKey": null,
    "unit": "Percent",
    "affectedProperties": [
      "ConsumableDataContainer.Reload.PCY022"
    ],
    "displayedValueProcessingKind": "DecimalRoundedPercentage",
    "valueProcessingKind": "Multiplier"
  },
  {
    "name": "invisible_fighterReloadCoeff",
    "value": 0.925,
    "gameLocalizationKey": "",
    "appLocalizationKey": null,
    "unit": "Percent",
    "affectedProperties": [
      "ConsumableDataContainer.Reload.PCY012.PCY038"
    ],
    "displayedValueProcessingKind": "DecimalRoundedPercentage",
    "valueProcessingKind": "Multiplier"
  },
  {
    "name": "invisible_rlsReloadCoeff",
    "value": 0.925,
    "gameLocalizationKey": "",
    "appLocalizationKey": null,
    "unit": "Percent",
    "affectedProperties": [
      "ConsumableDataContainer.Reload.PCY020"
    ],
    "displayedValueProcessingKind": "DecimalRoundedPercentage",
    "valueProcessingKind": "Multiplier"
  },
  {
    "name": "invisible_scoutReloadCoeff",
    "value": 0.925,
    "gameLocalizationKey": "",
    "appLocalizationKey": null,
    "unit": "Percent",
    "affectedProperties": [
      "ConsumableDataContainer.Reload.PCY013"
    ],
    "displayedValueProcessingKind": "DecimalRoundedPercentage",
    "valueProcessingKind": "Multiplier"
  },
  {
    "name": "invisible_smokeGeneratorReloadCoeff",
    "value": 0.925,
    "gameLocalizationKey": "",
    "appLocalizationKey": null,
    "unit": "Percent",
    "affectedProperties": [
      "ConsumableDataContainer.Reload.PCY014"
    ],
    "displayedValueProcessingKind": "DecimalRoundedPercentage",
    "valueProcessingKind": "Multiplier"
  },
  {
    "name": "invisible_sonarReloadCoeff",
    "value": 0.925,
    "gameLocalizationKey": "",
    "appLocalizationKey": null,
    "unit": "Percent",
    "affectedProperties": [
      "ConsumableDataContainer.Reload.PCY016"
    ],
    "displayedValueProcessingKind": "DecimalRoundedPercentage",
    "valueProcessingKind": "Multiplier"
  },
  {
    "name": "invisible_speedBoostersReloadCoeff",
    "value": 0.925,
    "gameLocalizationKey": "",
    "appLocalizationKey": null,
    "unit": "Percent",
    "affectedProperties": [
      "ConsumableDataContainer.Reload.PCY015"
    ],
    "displayedValueProcessingKind": "DecimalRoundedPercentage",
    "valueProcessingKind": "Multiplier"
  },
  {
    "name": "invisible_torpedoReloaderReloadCoeff",
    "value": 0.925,
    "gameLocalizationKey": "",
    "appLocalizationKey": null,
    "unit": "Percent",
    "affectedProperties": [
      "ConsumableDataContainer.Reload.PCY018"
    ],
    "displayedValueProcessingKind": "DecimalRoundedPercentage",
    "valueProcessingKind": "Multiplier"
  },
  {
    "name": "lastChanceReloadCoefficient",
    "value": 0.2,
    "gameLocalizationKey": "PARAMS_MODIFIER_LASTCHANCERELOADCOEFFICIENT",
    "appLocalizationKey": null,
    "unit": "Percent",
    "affectedProperties": [
      "MainBatteryDataContainer.Reload",
      "TorpedoArmamentDataContainer.Reload",
      "PingerGunDataContainer.Reload",
      "SecondaryBatteryDataContainer.Reload",
      "AntiAirDataContainer.ConstantDamage",
      "AirstrikeDataContainer.Reload"
    ],
    "displayedValueProcessingKind": "ToNegative",
    "valueProcessingKind": "NegativeMultiplier"
  },
  {
    "name": "lifeTime",
    "value": 10,
    "gameLocalizationKey": "PARAMS_MODIFIER_LIFETIME",
    "appLocalizationKey": null,
    "unit": "S",
    "affectedProperties": [],
    "displayedValueProcessingKind": "None",
    "valueProcessingKind": "None"
  },
  {
    "name": "maxBuoyancySpeedCoeff",
    "value": 1.2,
    "gameLocalizationKey": "PARAMS_MODIFIER_MAXBUOYANCYSPEEDCOEFF",
    "appLocalizationKey": null,
    "unit": "Percent",
    "affectedProperties": [
      "ManeuverabilityDataContainer.MaxDiveSpeed"
    ],
    "displayedValueProcessingKind": "DecimalRoundedPercentage",
    "valueProcessingKind": "Multiplier"
  },
  {
    "name": "pingerCritProb",
    "value": 0.75,
    "gameLocalizationKey": "PARAMS_MODIFIER_PINGERCRITPROB",
    "appLocalizationKey": null,
    "unit": "Percent",
    "affectedProperties": [],
    "displayedValueProcessingKind": "DecimalRoundedPercentage",
    "valueProcessingKind": "None"
  },
  {
    "name": "pingerReloadCoeff",
    "value": 0.9,
    "gameLocalizationKey": "PARAMS_MODIFIER_PINGERRELOADCOEFF_SKILL",
    "appLocalizationKey": null,
    "unit": "Percent",
    "affectedProperties": [
      "PingerGunDataContainer.Reload"
    ],
    "displayedValueProcessingKind": "DecimalRoundedPercentage",
    "valueProcessingKind": "Multiplier"
  },
  {
    "name": "pingerRepairTime",
    "value": 0.75,
    "gameLocalizationKey": "PARAMS_MODIFIER_PINGERREPAIRTIME",
    "appLocalizationKey": null,
    "unit": "Percent",
    "affectedProperties": [],
    "displayedValueProcessingKind": "DecimalRoundedPercentage",
    "valueProcessingKind": "None"
  },
  {
    "name": "pingerWaveSpeedCoeff",
    "value": 1.15,
    "gameLocalizationKey": "PARAMS_MODIFIER_PINGERWAVESPEEDCOEFF",
    "appLocalizationKey": null,
    "unit": "Percent",
    "affectedProperties": [
      "PingerGunDataContainer.WaveSpeed"
    ],
    "displayedValueProcessingKind": "DecimalRoundedPercentage",
    "valueProcessingKind": "Multiplier"
  },
  {
    "name": "planeAdditionalConsumables",
    "value": 1,
    "gameLocalizationKey": "PARAMS_MODIFIER_PLANEADDITIONALCONSUMABLES",
    "appLocalizationKey": null,
    "unit": "None",
    "affectedProperties": ["ConsumableDataContainer.Uses.Planes"],
    "displayedValueProcessingKind": "ToInt",
    "valueProcessingKind": "DirectAdd"
  },
  {
    "name": "planeBubbleArmorCoeff",
    "value": 0.75,
    "gameLocalizationKey": "PARAMS_MODIFIER_PLANEBUBBLEARMORCOEFF",
    "appLocalizationKey": null,
    "unit": "Percent",
    "affectedProperties": [],
    "displayedValueProcessingKind": "DecimalRoundedPercentage",
    "valueProcessingKind": "None"
  },
  {
    "name": "planeConsumablesWorkTime",
    "value": 1.5,
    "gameLocalizationKey": "PARAMS_MODIFIER_PLANECONSUMABLESWORKTIME",
    "appLocalizationKey": null,
    "unit": "Percent",
    "affectedProperties": [
      "ConsumableDataContainer.WorkTime.Plane"
    ],
    "displayedValueProcessingKind": "DecimalRoundedPercentage",
    "valueProcessingKind": "Multiplier"
  },
  {
    "name": "planeEmptyReturnSpeed",
    "value": 0.5,
    "gameLocalizationKey": "PARAMS_MODIFIER_PLANEEMPTYRETURNSPEED",
    "appLocalizationKey": null,
    "unit": "Percent",
    "affectedProperties": [],
    "displayedValueProcessingKind": "DecimalRoundedPercentage",
    "valueProcessingKind": "None"
  },
  {
    "name": "planeEscapeHeightCoeff",
    "value": 0.5,
    "gameLocalizationKey": "PARAMS_MODIFIER_PLANEESCAPEHEIGHTCOEFF",
    "appLocalizationKey": null,
    "unit": "Percent",
    "affectedProperties": [],
    "displayedValueProcessingKind": "DecimalRoundedPercentage",
    "valueProcessingKind": "None"
  },
  {
    "name": "planeExtraHangarSize",
    "value": 2,
    "gameLocalizationKey": "PARAMS_MODIFIER_PLANEEXTRAHANGARSIZE",
    "appLocalizationKey": null,
    "unit": "None",
    "affectedProperties": [
      "CvAircraftDataContainer.MaxOnDeck"
    ],
    "displayedValueProcessingKind": "ToInt",
    "valueProcessingKind": "DirectAdd"
  },
  {
    "name": "planeForsageTimeCoeff",
    "value": 1.05,
    "gameLocalizationKey": "PARAMS_MODIFIER_PLANEFORSAGETIMECOEFF",
    "appLocalizationKey": null,
    "unit": "Percent",
    "affectedProperties": [
      "CvAircraftDataContainer.BoostTime"
    ],
    "displayedValueProcessingKind": "DecimalRoundedPercentage",
    "valueProcessingKind": "Multiplier"
  },
  {
    "name": "planeHealthCoeff",
    "value": 1.075,
    "gameLocalizationKey": "PARAMS_MODIFIER_PLANEHEALTHCOEFF",
    "appLocalizationKey": null,
    "unit": "Percent",
    "affectedProperties": [
      "CvAircraftDataContainer.Hp"
    ],
    "displayedValueProcessingKind": "DecimalRoundedPercentage",
    "valueProcessingKind": "Multiplier"
  },
  {
    "name": "planeHealthPerLevel",
    "value": 25,
    "gameLocalizationKey": "PARAMS_MODIFIER_PLANEHEALTHPERLEVEL",
    "appLocalizationKey": null,
    "unit": "None",
    "affectedProperties": [
      "CvAircraftDataContainer.HpPerTier"
    ],
    "displayedValueProcessingKind": "ToInt",
    "valueProcessingKind": "Multiplier"
  },
  {
    "name": "planeMaxSpeedMultiplier",
    "value": 1.125,
    "gameLocalizationKey": "PARAMS_MODIFIER_PLANEMAXSPEEDMULTIPLIER",
    "appLocalizationKey": null,
    "unit": "Percent",
    "affectedProperties": [
      "CvAircraftDataContainer.MaxSpeed"
    ],
    "displayedValueProcessingKind": "DecimalRoundedPercentage",
    "valueProcessingKind": "Multiplier"
  },
  {
    "name": "planeSpawnTime",
    "value": 0.9,
    "gameLocalizationKey": "PARAMS_MODIFIER_PLANESPAWNTIME",
    "appLocalizationKey": null,
    "unit": "Percent",
    "affectedProperties": [
      "CvAircraftDataContainer.RestorationTime"
    ],
    "displayedValueProcessingKind": "DecimalRoundedPercentage",
    "valueProcessingKind": "Multiplier"
  },
  {
    "name": "planeSpeed",
    "value": 1.025,
    "gameLocalizationKey": "PARAMS_MODIFIER_PLANESPEED",
    "appLocalizationKey": null,
    "unit": "Percent",
    "affectedProperties": [
      "CvAircraftDataContainer.Speed"
    ],
    "displayedValueProcessingKind": "DecimalRoundedPercentage",
    "valueProcessingKind": "Multiplier"
  },
  {
    "name": "planeTorpedoArmingTimeCoeff",
    "value": 0.9,
    "gameLocalizationKey": "PARAMS_MODIFIER_PLANETORPEDOARMINGTIMECOEFF",
    "appLocalizationKey": null,
    "unit": "Percent",
    "affectedProperties": [
      "TorpedoDataContainer.ArmingTime"
    ],
    "displayedValueProcessingKind": "DecimalRoundedPercentage",
    "valueProcessingKind": "Multiplier"
  },
  {
    "name": "planeTorpedoSpeedMultiplier",
    "value": 1.05,
    "gameLocalizationKey": "PARAMS_MODIFIER_PLANETORPEDOSPEEDMULTIPLIER",
    "appLocalizationKey": null,
    "unit": "Percent",
    "affectedProperties": [
      "TorpedoDataContainer.Damage.Plane"
    ],
    "displayedValueProcessingKind": "DecimalRoundedPercentage",
    "valueProcessingKind": "Multiplier"
  },
  {
    "name": "planeVisibilityFactor",
    "value": 0.9,
    "gameLocalizationKey": "PARAMS_MODIFIER_PLANEVISIBILITYFACTOR",
    "appLocalizationKey": null,
    "unit": "Percent",
    "affectedProperties": [
      "CvAircraftDataContainer.Concealment",
      "ConsumableDataContainer.PCY035.Concealment",
      "ConsumableDataContainer.Concealment.PCY012.PCY03"
    ],
    "displayedValueProcessingKind": "DecimalRoundedPercentage",
    "valueProcessingKind": "Multiplier"
  },
  {
    "name": "PMDetonationProb",
    "value": 0.3,
    "gameLocalizationKey": "PARAMS_MODIFIER_PMDETONATIONPROB",
    "appLocalizationKey": null,
    "unit": "Percent",
    "affectedProperties": [],
    "displayedValueProcessingKind": "IntVariablePercentage",
    "valueProcessingKind": "None"
  },
  {
    "name": "prioritySectorCooldownMultiplier",
    "value": 0.8,
    "gameLocalizationKey": "PARAMS_MODIFIER_PRIORITYSECTORCOOLDOWNMULTIPLIER",
    "appLocalizationKey": null,
    "unit": "Percent",
    "affectedProperties": [],
    "displayedValueProcessingKind": "DecimalRoundedPercentage",
    "valueProcessingKind": "None"
  },
  {
    "name": "prioritySectorStartPhaseStrengthBonus",
    "value": 1.5,
    "gameLocalizationKey": "PARAMS_MODIFIER_PRIORITYSECTORSTARTPHASESTRENGTHBONUS",
    "appLocalizationKey": null,
    "unit": "Percent",
    "affectedProperties": [],
    "displayedValueProcessingKind": "NoneOrPercentage",
    "valueProcessingKind": "None"
  },
  {
    "name": "prioritySectorStrengthBonus",
    "value": 25,
    "gameLocalizationKey": "PARAMS_MODIFIER_PRIORITYSECTORSTRENGTHBONUS",
    "appLocalizationKey": null,
    "unit": "Percent",
    "affectedProperties": [],
    "displayedValueProcessingKind": "ToInt",
    "valueProcessingKind": "None"
  },
  {
    "name": "radius",
    "value": 15,
    "gameLocalizationKey": "PARAMS_MODIFIER_RADIUS",
    "appLocalizationKey": null,
    "unit": "KM",
    "affectedProperties": [],
    "displayedValueProcessingKind": "BigWorldToKmDecimal",
    "valueProcessingKind": "None"
  },
  {
    "name": "regenCrewAdditionalConsumables",
    "value": 1,
    "gameLocalizationKey": null,
    "appLocalizationKey": "regenCrewAdditionalConsumables",
    "unit": "None",
    "affectedProperties": [
      "ConsumableDataContainer.Uses.PCY010"
    ],
    "displayedValueProcessingKind": "ToInt",
    "valueProcessingKind": "DirectAdd"
  },
  {
    "name": "regenCrewReloadCoeff",
    "value": 0.992,
    "gameLocalizationKey": "PARAMS_MODIFIER_REGENCREWRELOADCOEFF_SKILL",
    "appLocalizationKey": null,
    "unit": "Percent",
    "affectedProperties": [
      "ConsumableDataContainer.Reload.PCY010"
    ],
    "displayedValueProcessingKind": "DecimalRoundedPercentage",
    "valueProcessingKind": "Multiplier"
  },
  {
    "name": "regenCrewWorkTimeCoeff",
    "value": 1.1,
    "gameLocalizationKey": "PARAMS_MODIFIER_REGENCREWWORKTIMECOEFF_SKILL",
    "appLocalizationKey": null,
    "unit": "Percent",
    "affectedProperties": [
      "ConsumableDataContainer.WorkTime.PCY010"
    ],
    "displayedValueProcessingKind": "DecimalRoundedPercentage",
    "valueProcessingKind": "Multiplier"
  },
  {
    "name": "regeneratedHPPartCoef",
    "value": 0.25,
    "gameLocalizationKey": "PARAMS_MODIFIER_REGENERATEDHPPARTCOEF",
    "appLocalizationKey": null,
    "unit": "Percent",
    "affectedProperties": [
      "SurvivabilityDataContainer.RepairableDamage"
    ],
    "displayedValueProcessingKind": "RoundedPercentage",
    "valueProcessingKind": "DirectAdd"
  },
  {
    "name": "regenerateHealthAdditionalConsumables",
    "value": 1,
    "gameLocalizationKey": "PARAMS_MODIFIER_REGENERATEHEALTHADDITIONALCONSUMABLES",
    "appLocalizationKey": null,
    "unit": "None",
    "affectedProperties": [
      "ConsumableDataContainer.Uses.PCY036"
    ],
    "displayedValueProcessingKind": "ToInt",
    "valueProcessingKind": "DirectAdd"
  },
  {
    "name": "regenerateHealthWorkTimeCoeff",
    "value": 1.1,
    "gameLocalizationKey": "PARAMS_MODIFIER_REGENERATEHEALTHWORKTIMECOEFF_SKILL",
    "appLocalizationKey": null,
    "unit": "Percent",
    "affectedProperties": [
      "ConsumableDataContainer.WorkTime.PCY036"
    ],
    "displayedValueProcessingKind": "DecimalRoundedPercentage",
    "valueProcessingKind": "Multiplier"
  },
  {
    "name": "regenerationRate",
    "value": 0.023,
    "gameLocalizationKey": "PARAMS_MODIFIER_REGENERATIONRATE",
    "appLocalizationKey": null,
    "unit": "PercentPerS",
    "affectedProperties": [],
    "displayedValueProcessingKind": "NoneOrPercentage",
    "valueProcessingKind": "None"
  },
  {
    "name": "repeatable_first_GMShotDelay",
    "value": 0.9,
    "gameLocalizationKey": null,
    "appLocalizationKey": "repeatable_first_GMShotDelay",
    "unit": "Percent",
    "affectedProperties": [
      "MainBatteryDataContainer.Reload"
    ],
    "displayedValueProcessingKind": "DecimalRoundedPercentage",
    "valueProcessingKind": "Multiplier"
  },
  {
    "name": "repeatable_other_GMShotDelay",
    "value": 0.95,
    "gameLocalizationKey": null,
    "appLocalizationKey": "repeatable_other_GMShotDelay",
    "unit": "Percent",
    "affectedProperties": [
      "MainBatteryDataContainer.Reload"
    ],
    "displayedValueProcessingKind": "DecimalRoundedPercentage",
    "valueProcessingKind": "Multiplier"
  },
  {
    "name": "rlsWorkTimeCoeff",
    "value": 1.1,
    "gameLocalizationKey": "PARAMS_MODIFIER_RLSWORKTIMECOEFF_SKILL",
    "appLocalizationKey": null,
    "unit": "Percent",
    "affectedProperties": [
      "ConsumableDataContainer.WorkTime.PCY020"
    ],
    "displayedValueProcessingKind": "DecimalRoundedPercentage",
    "valueProcessingKind": "Multiplier"
  },
  {
    "name": "rocketApAlphaDamageMultiplier",
    "value": 1.03,
    "gameLocalizationKey": "PARAMS_MODIFIER_ROCKETAPALPHADAMAGEMULTIPLIER",
    "appLocalizationKey": null,
    "unit": "Percent",
    "affectedProperties": [
      "RocketDataContainer.Damage.Ap"
    ],
    "displayedValueProcessingKind": "DecimalRoundedPercentage",
    "valueProcessingKind": "Multiplier"
  },
  {
    "name": "rocketBurnChanceBonus",
    "value": 0.01,
    "gameLocalizationKey": "PARAMS_MODIFIER_ROCKETBURNCHANCEBONUS",
    "appLocalizationKey": null,
    "unit": "Percent",
    "affectedProperties": [
      "RocketDataContainer.FireChance"
    ],
    "displayedValueProcessingKind": "NoneOrPercentage",
    "valueProcessingKind": "SumPercentage"
  },
  {
    "name": "scoutAdditionalConsumables",
    "value": 2,
    "gameLocalizationKey": "PARAMS_MODIFIER_SCOUTADDITIONALCONSUMABLES",
    "appLocalizationKey": null,
    "unit": "None",
    "affectedProperties": [
      "ConsumableDataContainer.Uses.PCY013"
    ],
    "displayedValueProcessingKind": "ToInt",
    "valueProcessingKind": "DirectAdd"
  },
  {
    "name": "scoutReloadCoeff",
    "value": 0.5,
    "gameLocalizationKey": "PARAMS_MODIFIER_SCOUTRELOADCOEFF_SKILL",
    "appLocalizationKey": null,
    "unit": "Percent",
    "affectedProperties": [
      "ConsumableDataContainer.Reload.PCY013"
    ],
    "displayedValueProcessingKind": "DecimalRoundedPercentage",
    "valueProcessingKind": "Multiplier"
  },
  {
    "name": "scoutWorkTimeCoeff",
    "value": 1.3,
    "gameLocalizationKey": "PARAMS_MODIFIER_SCOUTWORKTIMECOEFF",
    "appLocalizationKey": null,
    "unit": "Percent",
    "affectedProperties": [
      "ConsumableDataContainer.WorkTime.PCY013"
    ],
    "displayedValueProcessingKind": "DecimalRoundedPercentage",
    "valueProcessingKind": "Multiplier"
  },
  {
    "name": "secondSectorTimeCoeff",
    "value": 1.25,
    "gameLocalizationKey": "PARAMS_MODIFIER_SECONDSECTORTIMECOEFF",
    "appLocalizationKey": null,
    "unit": "Percent",
    "affectedProperties": [
      "PingerGunDataContainer.PingDuration.Second"
    ],
    "displayedValueProcessingKind": "DecimalRoundedPercentage",
    "valueProcessingKind": "Multiplier"
  },
  {
    "name": "SGCritProb",
    "value": 0.8,
    "gameLocalizationKey": "PARAMS_MODIFIER_SGCRITPROB",
    "appLocalizationKey": null,
    "unit": "Percent",
    "affectedProperties": [],
    "displayedValueProcessingKind": "DecimalRoundedPercentage",
    "valueProcessingKind": "None"
  },
  {
    "name": "SGCritRudderTime",
    "value": 2,
    "gameLocalizationKey": "PARAMS_MODIFIER_SGCRITRUDDERTIME",
    "appLocalizationKey": null,
    "unit": "Percent",
    "affectedProperties": [],
    "displayedValueProcessingKind": "VariablePercentage",
    "valueProcessingKind": "None"
  },
  {
    "name": "SGRepairTime",
    "value": 0.8,
    "gameLocalizationKey": "PARAMS_MODIFIER_SGREPAIRTIME",
    "appLocalizationKey": null,
    "unit": "Percent",
    "affectedProperties": [],
    "displayedValueProcessingKind": "DecimalRoundedPercentage",
    "valueProcessingKind": "None"
  },
  {
    "name": "SGRudderTime",
    "value": 0.9,
    "gameLocalizationKey": "PARAMS_MODIFIER_SGRUDDERTIME",
    "appLocalizationKey": null,
    "unit": "Percent",
    "affectedProperties": [
      "ManeuverabilityDataContainer.RudderShiftTime"
    ],
    "displayedValueProcessingKind": "DecimalRoundedPercentage",
    "valueProcessingKind": "Multiplier"
  },
  {
    "name": "shootShift",
    "value": 1.2,
    "gameLocalizationKey": "PARAMS_MODIFIER_SHOOTSHIFT",
    "appLocalizationKey": null,
    "unit": "Percent",
    "affectedProperties": [],
    "displayedValueProcessingKind": "DecimalRoundedPercentage",
    "valueProcessingKind": "None"
  },
  {
    "name": "skipBomberAccuracyIncRateCoeff",
    "value": 1.075,
    "gameLocalizationKey": "PARAMS_MODIFIER_SKIPBOMBERACCURACYINCRATECOEFF",
    "appLocalizationKey": null,
    "unit": "Percent",
    "affectedProperties": [
      "CvAircraftDataContainer.AimRate.SkipBomber"
    ],
    "displayedValueProcessingKind": "DecimalRoundedPercentage",
    "valueProcessingKind": "Multiplier"
  },
  {
    "name": "skipBomberAimingTime",
    "value": 2,
    "gameLocalizationKey": "PARAMS_MODIFIER_SKIPBOMBERAIMINGTIME",
    "appLocalizationKey": null,
    "unit": "S",
    "affectedProperties": [
      "CvAircraftDataContainer.AimingTime.SkipBomber"
    ],
    "displayedValueProcessingKind": "None",
    "valueProcessingKind": "Multiplier"
  },
  {
    "name": "skipBomberHealth",
    "value": 1.075,
    "gameLocalizationKey": "PARAMS_MODIFIER_SKIPBOMBERHEALTH",
    "appLocalizationKey": null,
    "unit": "Percent",
    "affectedProperties": [
      "CvAircraftDataContainer.Hp.SkipBomber"
    ],
    "displayedValueProcessingKind": "DecimalRoundedPercentage",
    "valueProcessingKind": "Multiplier"
  },
  {
    "name": "skipBomberSpeedMultiplier",
    "value": 1.05,
    "gameLocalizationKey": "PARAMS_MODIFIER_SKIPBOMBERSPEEDMULTIPLIER",
    "appLocalizationKey": null,
    "unit": "Percent",
    "affectedProperties": [
      "CvAircraftDataContainer.CruisingSpeed.SkipBomber"
    ],
    "displayedValueProcessingKind": "DecimalRoundedPercentage",
    "valueProcessingKind": "Multiplier"
  },
  {
    "name": "smokeGeneratorAdditionalConsumables",
    "value": 2,
    "gameLocalizationKey": "PARAMS_MODIFIER_SMOKEGENERATORADDITIONALCONSUMABLES",
    "appLocalizationKey": null,
    "unit": "None",
    "affectedProperties": [
      "ConsumableDataContainer.Uses.PCY014"
    ],
    "displayedValueProcessingKind": "ToPositive",
    "valueProcessingKind": "DirectAdd"
  },
  {
    "name": "smokeGeneratorLifeTime",
    "value": 1.2,
    "gameLocalizationKey": "PARAMS_MODIFIER_SMOKEGENERATORLIFETIME",
    "appLocalizationKey": null,
    "unit": "Percent",
    "affectedProperties": [
      "ConsumableDataContainer.LifeTime.PCY014"
    ],
    "displayedValueProcessingKind": "DecimalRoundedPercentage",
    "valueProcessingKind": "Multiplier"
  },
  {
    "name": "smokeGeneratorReloadCoeff",
    "value": 0.45,
    "gameLocalizationKey": "PARAMS_MODIFIER_SMOKEGENERATORRELOADCOEFF_MODERNIZATION",
    "appLocalizationKey": null,
    "unit": "Percent",
    "affectedProperties": [
      "ConsumableDataContainer.Reload.PCY014"
    ],
    "displayedValueProcessingKind": "DecimalRoundedPercentage",
    "valueProcessingKind": "Multiplier"
  },
  {
    "name": "smokeGeneratorWorkTimeCoeff",
    "value": 1.1,
    "gameLocalizationKey": "PARAMS_MODIFIER_SMOKEGENERATORWORKTIMECOEFF_SKILL",
    "appLocalizationKey": null,
    "unit": "Percent",
    "affectedProperties": [
      "ConsumableDataContainer.WorkTime.PCY014"
    ],
    "displayedValueProcessingKind": "DecimalRoundedPercentage",
    "valueProcessingKind": "Multiplier"
  },
  {
    "name": "sonarWorkTimeCoeff",
    "value": 1.1,
    "gameLocalizationKey": "PARAMS_MODIFIER_SONARWORKTIMECOEFF_SKILL",
    "appLocalizationKey": null,
    "unit": "Percent",
    "affectedProperties": [
      "ConsumableDataContainer.WorkTime.PCY016"
    ],
    "displayedValueProcessingKind": "DecimalRoundedPercentage",
    "valueProcessingKind": "Multiplier"
  },
  {
    "name": "spawnBackwardShift",
    "value": 0.4,
    "gameLocalizationKey": "",
    "appLocalizationKey": null,
    "unit": "Percent",
    "affectedProperties": [],
    "displayedValueProcessingKind": "DecimalRoundedPercentage",
    "valueProcessingKind": "None"
  },
  {
    "name": "spawnShiftRadius",
    "value": 0,
    "gameLocalizationKey": "",
    "appLocalizationKey": null,
    "unit": "None",
    "affectedProperties": [],
    "displayedValueProcessingKind": "ToInt",
    "valueProcessingKind": "None"
  },
  {
    "name": "speedBoostersWorkTimeCoeff",
    "value": 1.1,
    "gameLocalizationKey": "PARAMS_MODIFIER_SPEEDBOOSTERSWORKTIMECOEFF_SKILL",
    "appLocalizationKey": null,
    "unit": "Percent",
    "affectedProperties": [
      "ConsumableDataContainer.WorkTime.PCY015"
    ],
    "displayedValueProcessingKind": "DecimalRoundedPercentage",
    "valueProcessingKind": "Multiplier"
  },
  {
    "name": "speedCoef",
    "value": 1.08,
    "gameLocalizationKey": "PARAMS_MODIFIER_SPEEDCOEF",
    "appLocalizationKey": null,
    "unit": "Percent",
    "affectedProperties": [
      "ManeuverabilityDataContainer.Speed"
    ],
    "displayedValueProcessingKind": "DecimalRoundedPercentage",
    "valueProcessingKind": "Multiplier"
  },
  {
    "name": "speedCoefBattery",
    "value": 1.18,
    "gameLocalizationKey": "PARAMS_MODIFIER_SPEEDCOEFBATTERY",
    "appLocalizationKey": null,
    "unit": "Percent",
    "affectedProperties": [
      "ManeuverabilityDataContainer.PropellerShaftSpeed"
    ],
    "displayedValueProcessingKind": "DecimalRoundedPercentage",
    "valueProcessingKind": "Multiplier"
  },
  {
    "name": "speedLimit",
    "value": 12.5,
    "gameLocalizationKey": "",
    "appLocalizationKey": "ShipStats_SmokeSpeedLimit",
    "unit": "Knots",
    "affectedProperties": [],
    "displayedValueProcessingKind": "None",
    "valueProcessingKind": "None"
  },
  {
    "name": "startDelayTime",
    "value": 2,
    "gameLocalizationKey": "",
    "appLocalizationKey": null,
    "unit": "None",
    "affectedProperties": [],
    "displayedValueProcessingKind": "ToInt",
    "valueProcessingKind": "None"
  },
  {
    "name": "switchAmmoReloadCoef",
    "value": 0.4,
    "gameLocalizationKey": "PARAMS_MODIFIER_SWITCHAMMORELOADCOEF",
    "appLocalizationKey": null,
    "unit": "Percent",
    "affectedProperties": [],
    "displayedValueProcessingKind": "DecimalRoundedPercentage",
    "valueProcessingKind": "None"
  },
  {
    "name": "timeDelayAttack",
    "value": 5,
    "gameLocalizationKey": "PARAMS_MODIFIER_CALLFIGHTERSTIMEDELAYATTACK",
    "appLocalizationKey": null,
    "unit": "S",
    "affectedProperties": [],
    "displayedValueProcessingKind": "None",
    "valueProcessingKind": "None"
  },
  {
    "name": "timeFromHeaven",
    "value": 0,
    "gameLocalizationKey": "PARAMS_MODIFIER_CALLFIGHTERSAPPEARDELAY",
    "appLocalizationKey": null,
    "unit": "S",
    "affectedProperties": [],
    "displayedValueProcessingKind": "None",
    "valueProcessingKind": "None"
  },
  {
    "name": "timeToTryingCatch",
    "value": 40,
    "gameLocalizationKey": "",
    "appLocalizationKey": null,
    "unit": "None",
    "affectedProperties": [],
    "displayedValueProcessingKind": "ToInt",
    "valueProcessingKind": "None"
  },
  {
    "name": "timeWaitDelayAttack",
    "value": 10,
    "gameLocalizationKey": "",
    "appLocalizationKey": null,
    "unit": "None",
    "affectedProperties": [],
    "displayedValueProcessingKind": "ToInt",
    "valueProcessingKind": "None"
  },
  {
    "name": "torpedoBomberAccuracyIncRateCoeff",
    "value": 1.075,
    "gameLocalizationKey": "PARAMS_MODIFIER_TORPEDOBOMBERACCURACYINCRATECOEFF",
    "appLocalizationKey": null,
    "unit": "Percent",
    "affectedProperties": [
      "CvAircraftDataContainer.AimRate.TorpedoBomber"
    ],
    "displayedValueProcessingKind": "DecimalRoundedPercentage",
    "valueProcessingKind": "Multiplier"
  },
  {
    "name": "torpedoBomberAimingTime",
    "value": 5,
    "gameLocalizationKey": "PARAMS_MODIFIER_TORPEDOBOMBERAIMINGTIME",
    "appLocalizationKey": null,
    "unit": "S",
    "affectedProperties": [
      "CvAircraftDataContainer.AimingTime.TorpedoBomber"
    ],
    "displayedValueProcessingKind": "None",
    "valueProcessingKind": "DirectAdd"
  },
  {
    "name": "torpedoBomberHealth",
    "value": 1.15,
    "gameLocalizationKey": "PARAMS_MODIFIER_TORPEDOBOMBERHEALTH",
    "appLocalizationKey": null,
    "unit": "Percent",
    "affectedProperties": [
      "CvAircraftDataContainer.Hp.TorpedoBomber"
    ],
    "displayedValueProcessingKind": "DecimalRoundedPercentage",
    "valueProcessingKind": "Multiplier"
  },
  {
    "name": "torpedoDamageCoeff",
    "value": 1.15,
    "gameLocalizationKey": "PARAMS_MODIFIER_TORPEDODAMAGECOEFF",
    "appLocalizationKey": null,
    "unit": "Percent",
    "affectedProperties": [
      "TorpedoDataContainer.Damage"
    ],
    "displayedValueProcessingKind": "DecimalRoundedPercentage",
    "valueProcessingKind": "Multiplier"
  },
  {
    "name": "torpedoDetectionCoefficient",
    "value": 1.25,
    "gameLocalizationKey": "PARAMS_MODIFIER_TORPEDODETECTIONCOEFFICIENT",
    "appLocalizationKey": null,
    "unit": "Percent",
    "affectedProperties": [
      "ConsumableDataContainer.TorpDetection.PCY016"
    ],
    "displayedValueProcessingKind": "DecimalRoundedPercentage",
    "valueProcessingKind": "Multiplier"
  },
  {
    "name": "torpedoDetectionCoefficientByPlane",
    "value": 1,
    "gameLocalizationKey": "PARAMS_MODIFIER_TORPEDODETECTIONCOEFFICIENTBYPLANE",
    "appLocalizationKey": null,
    "unit": "None",
    "affectedProperties": [],
    "displayedValueProcessingKind": "Empty",
    "valueProcessingKind": "None"
  },
  {
    "name": "torpedoFullPingDamageCoeff",
    "value": 1.15,
    "gameLocalizationKey": "PARAMS_MODIFIER_TORPEDOFULLPINGDAMAGECOEFF",
    "appLocalizationKey": null,
    "unit": "Percent",
    "affectedProperties": [],
    "displayedValueProcessingKind": "DecimalRoundedPercentage",
    "valueProcessingKind": "None"
  },
  {
    "name": "torpedoReloaderAdditionalConsumables",
    "value": 1,
    "gameLocalizationKey": "PARAMS_MODIFIER_TORPEDORELOADERADDITIONALCONSUMABLES",
    "appLocalizationKey": null,
    "unit": "None",
    "affectedProperties": ["ConsumableDataContainer.Uses.PCY018"],
    "displayedValueProcessingKind": "ToInt",
    "valueProcessingKind": "DirectAdd"
  },
  {
    "name": "torpedoReloaderReloadCoeff",
    "value": 0.75,
    "gameLocalizationKey": "PARAMS_MODIFIER_TORPEDORELOADERRELOADCOEFF_SKILL",
    "appLocalizationKey": null,
    "unit": "Percent",
    "affectedProperties": [
      "ConsumableDataContainer.Reload.PCY018"
    ],
    "displayedValueProcessingKind": "DecimalRoundedPercentage",
    "valueProcessingKind": "Multiplier"
  },
  {
    "name": "torpedoReloadTime",
    "value": 5,
    "gameLocalizationKey": "PARAMS_MODIFIER_TORPEDORELOADTIME",
    "appLocalizationKey": null,
    "unit": "S",
    "affectedProperties": [],
    "displayedValueProcessingKind": "None",
    "valueProcessingKind": "None"
  },
  {
    "name": "torpedoSpeedMultiplier",
    "value": 1.07,
    "gameLocalizationKey": "PARAMS_MODIFIER_TORPEDOSPEEDMULTIPLIER",
    "appLocalizationKey": null,
    "unit": "Percent",
    "affectedProperties": [
      "TorpedoDataContainer.Damage.Ship"
    ],
    "displayedValueProcessingKind": "DecimalRoundedPercentage",
    "valueProcessingKind": "Multiplier"
  },
  {
    "name": "torpedoVisibilityFactor",
    "value": 0.9,
    "gameLocalizationKey": "PARAMS_MODIFIER_TORPEDOVISIBILITYFACTOR",
    "appLocalizationKey": null,
    "unit": "Percent",
    "affectedProperties": [
      "TorpedoDataContainer.Visibility"
    ],
    "displayedValueProcessingKind": "DecimalRoundedPercentage",
    "valueProcessingKind": "Multiplier"
  },
  {
    "name": "underwaterMaxRudderAngleCoeff",
    "value": 1,
    "gameLocalizationKey": "",
    "appLocalizationKey": null,
    "unit": "None",
    "affectedProperties": [],
    "displayedValueProcessingKind": "ToInt",
    "valueProcessingKind": "None"
  },
  {
    "name": "updatePeriod",
    "value": 1,
    "gameLocalizationKey": "",
    "appLocalizationKey": null,
    "unit": "None",
    "affectedProperties": [],
    "displayedValueProcessingKind": "ToInt",
    "valueProcessingKind": "None"
  },
  {
    "name": "uwCoeffBonus",
    "value": 7,
    "gameLocalizationKey": "PARAMS_MODIFIER_UWCOEFFBONUS",
    "appLocalizationKey": null,
    "unit": "Percent",
    "affectedProperties": [
      "SurvivabilityDataContainer.FloodChance"
    ],
    "displayedValueProcessingKind": "ToInt",
    "valueProcessingKind": "SubtractPercentage"
  },
  {
    "name": "visibilityDistCoeff",
    "value": 0.9,
    "gameLocalizationKey": "PARAMS_MODIFIER_VISIBILITYDISTCOEFF_DESTROYER",
    "appLocalizationKey": null,
    "unit": "Percent",
    "affectedProperties": [
      "ConcealmentDataContainer.Visibility"
    ],
    "displayedValueProcessingKind": "DecimalRoundedPercentage",
    "valueProcessingKind": "Multiplier"
  },
  {
    "name": "visibilityForSubmarineCoeff",
    "value": 0.9,
    "gameLocalizationKey": "PARAMS_MODIFIER_VISIBILITYFORSUBMARINECOEFF",
    "appLocalizationKey": null,
    "unit": "Percent",
    "affectedProperties": [],
    "displayedValueProcessingKind": "DecimalRoundedPercentage",
    "valueProcessingKind": "None"
  },
  {
    "name": "visionXRayTorpedoDist",
    "value": 1800,
    "gameLocalizationKey": "PARAMS_MODIFIER_VISIONXRAYTORPEDODIST",
    "appLocalizationKey": null,
    "unit": "KM",
    "affectedProperties": [],
    "displayedValueProcessingKind": "MeterToKm",
    "valueProcessingKind": "None"
  },
  {
    "name": "vulnerabilityBurn",
    "value": 0.9,
    "gameLocalizationKey": "PARAMS_MODIFIER_VULNERABILITYBURN",
    "appLocalizationKey": null,
    "unit": "Percent",
    "affectedProperties": [
      "SurvivabilityDataContainer.FireDamageWeakness"
    ],
    "displayedValueProcessingKind": "DecimalRoundedPercentage",
    "valueProcessingKind": "Multiplier"
  },
  {
    "name": "vulnerabilityFlood",
    "value": 0.9,
    "gameLocalizationKey": "PARAMS_MODIFIER_VULNERABILITYFLOOD",
    "appLocalizationKey": null,
    "unit": "Percent",
    "affectedProperties": [
      "SurvivabilityDataContainer.FloodDamageWeakness"
    ],
    "displayedValueProcessingKind": "DecimalRoundedPercentage",
    "valueProcessingKind": "Multiplier"
  },
  {
    "name": "workTime",
    "value": 15,
    "gameLocalizationKey": "PARAMS_MODIFIER_WORKTIME",
    "appLocalizationKey": null,
    "unit": "None",
    "affectedProperties": [],
    "displayedValueProcessingKind": "ToInt",
    "valueProcessingKind": "None"
  },
  {
    "name": "zoneLifetime",
    "value": 4,
    "gameLocalizationKey": "",
    "appLocalizationKey": null,
    "unit": "None",
    "affectedProperties": [],
    "displayedValueProcessingKind": "ToInt",
    "valueProcessingKind": "None"
  }
]